{
  "code": "6239",
  "symbol": "TWSE:6239",
  "name": "力成",
  "sector": "封裝測試",
  "market": "TW",
  "data_date": "2026-05-21",
  "version": "2.1",
  "ohlcv": [
    {
      "time": "2025-08-20",
      "open": 120.0,
      "high": 120.0,
      "low": 116.5,
      "close": 116.5,
      "volume": 3211400.0
    },
    {
      "time": "2025-08-21",
      "open": 117.5,
      "high": 119.5,
      "low": 117.5,
      "close": 119.5,
      "volume": 2596572.0
    },
    {
      "time": "2025-08-22",
      "open": 119.5,
      "high": 119.5,
      "low": 116.0,
      "close": 117.0,
      "volume": 1862340.0
    },
    {
      "time": "2025-08-25",
      "open": 119.0,
      "high": 120.0,
      "low": 118.0,
      "close": 118.5,
      "volume": 1256139.0
    },
    {
      "time": "2025-08-26",
      "open": 118.5,
      "high": 120.5,
      "low": 118.5,
      "close": 118.5,
      "volume": 3380400.0
    },
    {
      "time": "2025-08-27",
      "open": 119.0,
      "high": 120.0,
      "low": 119.0,
      "close": 119.5,
      "volume": 1287069.0
    },
    {
      "time": "2025-08-28",
      "open": 119.5,
      "high": 120.0,
      "low": 118.5,
      "close": 118.5,
      "volume": 2061567.0
    },
    {
      "time": "2025-08-29",
      "open": 119.0,
      "high": 120.5,
      "low": 118.0,
      "close": 119.0,
      "volume": 2299339.0
    },
    {
      "time": "2025-09-01",
      "open": 119.5,
      "high": 121.0,
      "low": 118.0,
      "close": 119.0,
      "volume": 2003776.0
    },
    {
      "time": "2025-09-02",
      "open": 120.0,
      "high": 123.0,
      "low": 119.0,
      "close": 119.5,
      "volume": 4403606.0
    },
    {
      "time": "2025-09-03",
      "open": 120.0,
      "high": 121.0,
      "low": 118.0,
      "close": 119.5,
      "volume": 2456348.0
    },
    {
      "time": "2025-09-04",
      "open": 120.5,
      "high": 121.5,
      "low": 119.0,
      "close": 120.0,
      "volume": 2117739.0
    },
    {
      "time": "2025-09-05",
      "open": 121.0,
      "high": 121.0,
      "low": 119.5,
      "close": 120.5,
      "volume": 2015341.0
    },
    {
      "time": "2025-09-08",
      "open": 123.0,
      "high": 128.5,
      "low": 123.0,
      "close": 126.5,
      "volume": 9501092.0
    },
    {
      "time": "2025-09-09",
      "open": 126.5,
      "high": 127.0,
      "low": 125.0,
      "close": 126.0,
      "volume": 5001863.0
    },
    {
      "time": "2025-09-10",
      "open": 126.0,
      "high": 127.5,
      "low": 126.0,
      "close": 127.0,
      "volume": 3401207.0
    },
    {
      "time": "2025-09-11",
      "open": 130.0,
      "high": 134.0,
      "low": 129.0,
      "close": 129.5,
      "volume": 9119736.0
    },
    {
      "time": "2025-09-12",
      "open": 134.5,
      "high": 142.0,
      "low": 133.0,
      "close": 142.0,
      "volume": 24876880.0
    },
    {
      "time": "2025-09-15",
      "open": 142.0,
      "high": 152.5,
      "low": 139.0,
      "close": 151.0,
      "volume": 34410517.0
    },
    {
      "time": "2025-09-16",
      "open": 149.5,
      "high": 151.0,
      "low": 145.5,
      "close": 148.5,
      "volume": 24389433.0
    },
    {
      "time": "2025-09-17",
      "open": 150.0,
      "high": 151.0,
      "low": 143.0,
      "close": 145.0,
      "volume": 15467208.0
    },
    {
      "time": "2025-09-18",
      "open": 149.0,
      "high": 153.0,
      "low": 147.0,
      "close": 149.5,
      "volume": 22666399.0
    },
    {
      "time": "2025-09-19",
      "open": 152.0,
      "high": 153.5,
      "low": 148.5,
      "close": 150.5,
      "volume": 14015693.0
    },
    {
      "time": "2025-09-22",
      "open": 151.5,
      "high": 152.5,
      "low": 149.5,
      "close": 151.0,
      "volume": 8525574.0
    },
    {
      "time": "2025-09-23",
      "open": 152.0,
      "high": 153.0,
      "low": 148.5,
      "close": 150.5,
      "volume": 7772318.0
    },
    {
      "time": "2025-09-24",
      "open": 150.5,
      "high": 151.5,
      "low": 148.0,
      "close": 151.0,
      "volume": 7720178.0
    },
    {
      "time": "2025-09-25",
      "open": 150.0,
      "high": 150.5,
      "low": 148.5,
      "close": 150.5,
      "volume": 5064121.0
    },
    {
      "time": "2025-09-26",
      "open": 149.5,
      "high": 149.5,
      "low": 138.5,
      "close": 140.0,
      "volume": 13810763.0
    },
    {
      "time": "2025-09-30",
      "open": 142.5,
      "high": 146.0,
      "low": 141.0,
      "close": 146.0,
      "volume": 7061314.0
    },
    {
      "time": "2025-10-01",
      "open": 147.5,
      "high": 148.0,
      "low": 145.0,
      "close": 147.0,
      "volume": 5961232.0
    },
    {
      "time": "2025-10-02",
      "open": 152.5,
      "high": 155.5,
      "low": 149.5,
      "close": 151.0,
      "volume": 14625553.0
    },
    {
      "time": "2025-10-03",
      "open": 150.5,
      "high": 152.5,
      "low": 149.5,
      "close": 152.0,
      "volume": 5458699.0
    },
    {
      "time": "2025-10-07",
      "open": 154.5,
      "high": 160.0,
      "low": 153.5,
      "close": 158.0,
      "volume": 11749723.0
    },
    {
      "time": "2025-10-08",
      "open": 156.0,
      "high": 160.0,
      "low": 154.5,
      "close": 158.0,
      "volume": 7116019.0
    },
    {
      "time": "2025-10-09",
      "open": 160.0,
      "high": 162.0,
      "low": 158.0,
      "close": 159.0,
      "volume": 10137588.0
    },
    {
      "time": "2025-10-13",
      "open": 150.0,
      "high": 156.0,
      "low": 149.0,
      "close": 153.5,
      "volume": 6811026.0
    },
    {
      "time": "2025-10-14",
      "open": 155.5,
      "high": 156.5,
      "low": 147.0,
      "close": 147.5,
      "volume": 10016800.0
    },
    {
      "time": "2025-10-15",
      "open": 150.5,
      "high": 151.0,
      "low": 147.0,
      "close": 150.0,
      "volume": 5222377.0
    },
    {
      "time": "2025-10-16",
      "open": 152.5,
      "high": 158.0,
      "low": 152.5,
      "close": 156.0,
      "volume": 7909421.0
    },
    {
      "time": "2025-10-17",
      "open": 155.5,
      "high": 157.0,
      "low": 153.5,
      "close": 153.5,
      "volume": 4632165.0
    },
    {
      "time": "2025-10-20",
      "open": 156.0,
      "high": 157.0,
      "low": 153.5,
      "close": 156.0,
      "volume": 3110933.0
    },
    {
      "time": "2025-10-21",
      "open": 158.0,
      "high": 158.0,
      "low": 152.0,
      "close": 152.0,
      "volume": 4200477.0
    },
    {
      "time": "2025-10-22",
      "open": 152.0,
      "high": 153.0,
      "low": 150.0,
      "close": 151.5,
      "volume": 3083295.0
    },
    {
      "time": "2025-10-23",
      "open": 150.5,
      "high": 151.5,
      "low": 149.0,
      "close": 150.0,
      "volume": 2773372.0
    },
    {
      "time": "2025-10-27",
      "open": 156.0,
      "high": 164.5,
      "low": 156.0,
      "close": 160.5,
      "volume": 15322421.0
    },
    {
      "time": "2025-10-28",
      "open": 163.0,
      "high": 176.5,
      "low": 161.5,
      "close": 176.5,
      "volume": 26686383.0
    },
    {
      "time": "2025-10-29",
      "open": 180.0,
      "high": 185.5,
      "low": 175.0,
      "close": 182.0,
      "volume": 50000697.0
    },
    {
      "time": "2025-10-30",
      "open": 183.0,
      "high": 185.0,
      "low": 175.0,
      "close": 177.0,
      "volume": 17060603.0
    },
    {
      "time": "2025-10-31",
      "open": 178.5,
      "high": 183.0,
      "low": 172.5,
      "close": 173.0,
      "volume": 14106231.0
    },
    {
      "time": "2025-11-03",
      "open": 173.0,
      "high": 176.0,
      "low": 169.5,
      "close": 173.0,
      "volume": 9922460.0
    },
    {
      "time": "2025-11-04",
      "open": 178.5,
      "high": 180.5,
      "low": 174.0,
      "close": 174.0,
      "volume": 22428985.0
    },
    {
      "time": "2025-11-05",
      "open": 168.0,
      "high": 175.0,
      "low": 165.5,
      "close": 172.5,
      "volume": 15981054.0
    },
    {
      "time": "2025-11-06",
      "open": 174.0,
      "high": 174.5,
      "low": 167.0,
      "close": 170.0,
      "volume": 13098349.0
    },
    {
      "time": "2025-11-07",
      "open": 170.0,
      "high": 173.0,
      "low": 166.0,
      "close": 170.0,
      "volume": 10690692.0
    },
    {
      "time": "2025-11-10",
      "open": 171.0,
      "high": 173.0,
      "low": 164.5,
      "close": 172.0,
      "volume": 15523655.0
    },
    {
      "time": "2025-11-11",
      "open": 173.5,
      "high": 177.5,
      "low": 168.0,
      "close": 169.5,
      "volume": 15520704.0
    },
    {
      "time": "2025-11-12",
      "open": 170.0,
      "high": 172.5,
      "low": 167.0,
      "close": 168.0,
      "volume": 8651183.0
    },
    {
      "time": "2025-11-13",
      "open": 171.5,
      "high": 174.5,
      "low": 168.5,
      "close": 170.0,
      "volume": 16932692.0
    },
    {
      "time": "2025-11-14",
      "open": 165.5,
      "high": 166.0,
      "low": 160.0,
      "close": 160.5,
      "volume": 11552084.0
    },
    {
      "time": "2025-11-17",
      "open": 164.0,
      "high": 167.5,
      "low": 161.0,
      "close": 164.5,
      "volume": 11983611.0
    },
    {
      "time": "2025-11-18",
      "open": 162.0,
      "high": 165.5,
      "low": 160.0,
      "close": 160.5,
      "volume": 12755414.0
    },
    {
      "time": "2025-11-19",
      "open": 159.0,
      "high": 159.5,
      "low": 153.0,
      "close": 154.0,
      "volume": 10946283.0
    },
    {
      "time": "2025-11-20",
      "open": 160.0,
      "high": 161.5,
      "low": 157.0,
      "close": 158.5,
      "volume": 9120046.0
    },
    {
      "time": "2025-11-21",
      "open": 151.0,
      "high": 153.5,
      "low": 149.0,
      "close": 151.0,
      "volume": 7972428.0
    },
    {
      "time": "2025-11-24",
      "open": 152.5,
      "high": 153.0,
      "low": 148.0,
      "close": 151.5,
      "volume": 6408860.0
    },
    {
      "time": "2025-11-25",
      "open": 155.0,
      "high": 155.0,
      "low": 151.0,
      "close": 152.0,
      "volume": 4108361.0
    },
    {
      "time": "2025-11-26",
      "open": 152.5,
      "high": 154.5,
      "low": 151.0,
      "close": 154.5,
      "volume": 4022228.0
    },
    {
      "time": "2025-11-27",
      "open": 155.5,
      "high": 156.5,
      "low": 154.5,
      "close": 155.5,
      "volume": 3772581.0
    },
    {
      "time": "2025-11-28",
      "open": 156.5,
      "high": 158.5,
      "low": 155.0,
      "close": 157.0,
      "volume": 3164560.0
    },
    {
      "time": "2025-12-01",
      "open": 159.0,
      "high": 159.0,
      "low": 153.0,
      "close": 153.5,
      "volume": 6457847.0
    },
    {
      "time": "2025-12-02",
      "open": 154.0,
      "high": 157.5,
      "low": 153.5,
      "close": 155.5,
      "volume": 4605514.0
    },
    {
      "time": "2025-12-03",
      "open": 157.5,
      "high": 161.5,
      "low": 156.5,
      "close": 158.5,
      "volume": 7053961.0
    },
    {
      "time": "2025-12-04",
      "open": 158.5,
      "high": 158.5,
      "low": 154.0,
      "close": 156.0,
      "volume": 6120583.0
    },
    {
      "time": "2025-12-05",
      "open": 156.5,
      "high": 157.5,
      "low": 155.0,
      "close": 157.0,
      "volume": 3762356.0
    },
    {
      "time": "2025-12-08",
      "open": 159.5,
      "high": 161.5,
      "low": 157.5,
      "close": 160.0,
      "volume": 6122145.0
    },
    {
      "time": "2025-12-09",
      "open": 161.5,
      "high": 164.0,
      "low": 160.0,
      "close": 160.5,
      "volume": 6476257.0
    },
    {
      "time": "2025-12-10",
      "open": 161.5,
      "high": 162.0,
      "low": 157.5,
      "close": 159.0,
      "volume": 5793251.0
    },
    {
      "time": "2025-12-11",
      "open": 160.0,
      "high": 164.5,
      "low": 158.5,
      "close": 162.0,
      "volume": 6452161.0
    },
    {
      "time": "2025-12-12",
      "open": 162.5,
      "high": 167.0,
      "low": 161.5,
      "close": 162.0,
      "volume": 7978882.0
    },
    {
      "time": "2025-12-15",
      "open": 159.0,
      "high": 161.5,
      "low": 156.5,
      "close": 159.0,
      "volume": 9865571.0
    },
    {
      "time": "2025-12-16",
      "open": 158.5,
      "high": 161.5,
      "low": 152.0,
      "close": 155.5,
      "volume": 12512707.0
    },
    {
      "time": "2025-12-17",
      "open": 156.5,
      "high": 165.0,
      "low": 156.0,
      "close": 162.0,
      "volume": 12984458.0
    },
    {
      "time": "2025-12-18",
      "open": 164.5,
      "high": 165.0,
      "low": 160.0,
      "close": 161.5,
      "volume": 10739227.0
    },
    {
      "time": "2025-12-19",
      "open": 165.0,
      "high": 165.0,
      "low": 159.0,
      "close": 159.0,
      "volume": 9776073.0
    },
    {
      "time": "2025-12-22",
      "open": 164.0,
      "high": 174.5,
      "low": 164.0,
      "close": 172.0,
      "volume": 22521829.0
    },
    {
      "time": "2025-12-23",
      "open": 170.0,
      "high": 171.0,
      "low": 163.0,
      "close": 164.0,
      "volume": 15214683.0
    },
    {
      "time": "2025-12-24",
      "open": 164.0,
      "high": 166.5,
      "low": 162.0,
      "close": 164.5,
      "volume": 9861013.0
    },
    {
      "time": "2025-12-26",
      "open": 169.5,
      "high": 180.0,
      "low": 166.5,
      "close": 175.0,
      "volume": 33706193.0
    },
    {
      "time": "2025-12-29",
      "open": 175.0,
      "high": 177.5,
      "low": 169.5,
      "close": 176.5,
      "volume": 15895382.0
    },
    {
      "time": "2025-12-30",
      "open": 176.5,
      "high": 177.5,
      "low": 173.0,
      "close": 175.0,
      "volume": 7414858.0
    },
    {
      "time": "2025-12-31",
      "open": 175.0,
      "high": 179.0,
      "low": 173.0,
      "close": 173.0,
      "volume": 10070269.0
    },
    {
      "time": "2026-01-02",
      "open": 175.0,
      "high": 185.0,
      "low": 173.5,
      "close": 183.5,
      "volume": 20224536.0
    },
    {
      "time": "2026-01-05",
      "open": 192.0,
      "high": 201.5,
      "low": 185.5,
      "close": 201.5,
      "volume": 32738272.0
    },
    {
      "time": "2026-01-06",
      "open": 199.0,
      "high": 209.0,
      "low": 197.5,
      "close": 204.0,
      "volume": 38510848.0
    },
    {
      "time": "2026-01-07",
      "open": 211.0,
      "high": 214.0,
      "low": 203.0,
      "close": 205.5,
      "volume": 27622288.0
    },
    {
      "time": "2026-01-08",
      "open": 206.0,
      "high": 207.0,
      "low": 199.0,
      "close": 203.0,
      "volume": 13994086.0
    },
    {
      "time": "2026-01-09",
      "open": 203.0,
      "high": 203.0,
      "low": 190.5,
      "close": 200.0,
      "volume": 19559759.0
    },
    {
      "time": "2026-01-12",
      "open": 210.5,
      "high": 220.0,
      "low": 206.5,
      "close": 220.0,
      "volume": 26466782.0
    },
    {
      "time": "2026-01-13",
      "open": 231.0,
      "high": 242.0,
      "low": 230.0,
      "close": 242.0,
      "volume": 38182108.0
    },
    {
      "time": "2026-01-14",
      "open": 245.5,
      "high": 253.5,
      "low": 241.0,
      "close": 251.5,
      "volume": 47909243.0
    },
    {
      "time": "2026-01-15",
      "open": 250.0,
      "high": 257.5,
      "low": 247.5,
      "close": 257.5,
      "volume": 18346219.0
    },
    {
      "time": "2026-01-16",
      "open": 258.0,
      "high": 269.0,
      "low": 254.0,
      "close": 263.0,
      "volume": 19776713.0
    },
    {
      "time": "2026-01-19",
      "open": 265.0,
      "high": 271.5,
      "low": 258.5,
      "close": 262.5,
      "volume": 22077114.0
    },
    {
      "time": "2026-01-20",
      "open": 257.0,
      "high": 258.0,
      "low": 249.0,
      "close": 251.5,
      "volume": 19133488.0
    },
    {
      "time": "2026-01-21",
      "open": 251.0,
      "high": 255.0,
      "low": 238.0,
      "close": 239.5,
      "volume": 22835862.0
    },
    {
      "time": "2026-01-22",
      "open": 249.0,
      "high": 263.0,
      "low": 247.0,
      "close": 257.5,
      "volume": 27202804.0
    },
    {
      "time": "2026-01-23",
      "open": 257.5,
      "high": 257.5,
      "low": 245.5,
      "close": 246.5,
      "volume": 16035277.0
    },
    {
      "time": "2026-01-26",
      "open": 250.0,
      "high": 259.5,
      "low": 248.0,
      "close": 257.5,
      "volume": 14568688.0
    },
    {
      "time": "2026-01-27",
      "open": 262.0,
      "high": 280.0,
      "low": 258.0,
      "close": 263.5,
      "volume": 27034644.0
    },
    {
      "time": "2026-01-28",
      "open": 275.0,
      "high": 275.0,
      "low": 253.0,
      "close": 261.5,
      "volume": 42383513.0
    },
    {
      "time": "2026-01-29",
      "open": 265.0,
      "high": 269.0,
      "low": 251.0,
      "close": 255.5,
      "volume": 23718413.0
    },
    {
      "time": "2026-01-30",
      "open": 255.0,
      "high": 261.0,
      "low": 250.0,
      "close": 254.0,
      "volume": 14962684.0
    },
    {
      "time": "2026-02-02",
      "open": 250.5,
      "high": 251.5,
      "low": 238.0,
      "close": 244.5,
      "volume": 12320170.0
    },
    {
      "time": "2026-02-03",
      "open": 254.5,
      "high": 262.0,
      "low": 252.5,
      "close": 257.0,
      "volume": 15716294.0
    },
    {
      "time": "2026-02-04",
      "open": 255.0,
      "high": 258.0,
      "low": 249.0,
      "close": 252.5,
      "volume": 8161323.0
    },
    {
      "time": "2026-02-05",
      "open": 248.5,
      "high": 249.0,
      "low": 241.0,
      "close": 244.0,
      "volume": 9558869.0
    },
    {
      "time": "2026-02-06",
      "open": 243.0,
      "high": 244.5,
      "low": 232.0,
      "close": 239.5,
      "volume": 12296445.0
    },
    {
      "time": "2026-02-09",
      "open": 248.0,
      "high": 253.5,
      "low": 243.0,
      "close": 243.0,
      "volume": 9794886.0
    },
    {
      "time": "2026-02-10",
      "open": 247.0,
      "high": 247.0,
      "low": 238.5,
      "close": 240.0,
      "volume": 6978058.0
    },
    {
      "time": "2026-02-11",
      "open": 236.5,
      "high": 244.0,
      "low": 236.5,
      "close": 243.0,
      "volume": 5723308.0
    },
    {
      "time": "2026-02-23",
      "open": 246.5,
      "high": 256.0,
      "low": 245.5,
      "close": 249.0,
      "volume": 13941918.0
    },
    {
      "time": "2026-02-24",
      "open": 250.5,
      "high": 263.0,
      "low": 250.5,
      "close": 257.5,
      "volume": 13295771.0
    },
    {
      "time": "2026-02-25",
      "open": 261.0,
      "high": 261.0,
      "low": 251.0,
      "close": 258.0,
      "volume": 12598461.0
    },
    {
      "time": "2026-02-26",
      "open": 259.0,
      "high": 261.0,
      "low": 249.0,
      "close": 258.0,
      "volume": 11824885.0
    },
    {
      "time": "2026-03-02",
      "open": 250.0,
      "high": 255.0,
      "low": 248.5,
      "close": 253.0,
      "volume": 8130389.0
    },
    {
      "time": "2026-03-03",
      "open": 253.0,
      "high": 255.5,
      "low": 228.0,
      "close": 231.0,
      "volume": 16095190.0
    },
    {
      "time": "2026-03-04",
      "open": 219.5,
      "high": 225.0,
      "low": 211.0,
      "close": 217.0,
      "volume": 17470816.0
    },
    {
      "time": "2026-03-05",
      "open": 229.5,
      "high": 230.0,
      "low": 219.5,
      "close": 224.5,
      "volume": 8740623.0
    },
    {
      "time": "2026-03-06",
      "open": 225.5,
      "high": 228.0,
      "low": 220.0,
      "close": 225.0,
      "volume": 6359117.0
    },
    {
      "time": "2026-03-09",
      "open": 209.0,
      "high": 209.5,
      "low": 202.5,
      "close": 202.5,
      "volume": 9323105.0
    },
    {
      "time": "2026-03-10",
      "open": 212.0,
      "high": 218.0,
      "low": 208.5,
      "close": 214.5,
      "volume": 8259062.0
    },
    {
      "time": "2026-03-11",
      "open": 217.5,
      "high": 220.0,
      "low": 215.5,
      "close": 215.5,
      "volume": 9337866.0
    },
    {
      "time": "2026-03-12",
      "open": 210.0,
      "high": 212.5,
      "low": 201.0,
      "close": 204.5,
      "volume": 10237928.0
    },
    {
      "time": "2026-03-13",
      "open": 198.5,
      "high": 203.0,
      "low": 196.5,
      "close": 201.0,
      "volume": 11696176.0
    },
    {
      "time": "2026-03-16",
      "open": 205.0,
      "high": 210.5,
      "low": 201.0,
      "close": 204.0,
      "volume": 8595702.0
    },
    {
      "time": "2026-03-17",
      "open": 207.0,
      "high": 209.0,
      "low": 200.0,
      "close": 202.5,
      "volume": 11335730.0
    },
    {
      "time": "2026-03-18",
      "open": 206.0,
      "high": 215.0,
      "low": 205.0,
      "close": 211.0,
      "volume": 18468581.0
    },
    {
      "time": "2026-03-19",
      "open": 210.0,
      "high": 213.0,
      "low": 205.0,
      "close": 205.5,
      "volume": 9141324.0
    },
    {
      "time": "2026-03-20",
      "open": 208.5,
      "high": 210.0,
      "low": 197.5,
      "close": 201.5,
      "volume": 10318300.0
    },
    {
      "time": "2026-03-23",
      "open": 193.5,
      "high": 196.0,
      "low": 190.0,
      "close": 192.0,
      "volume": 9255412.0
    },
    {
      "time": "2026-03-24",
      "open": 199.0,
      "high": 199.0,
      "low": 188.0,
      "close": 192.0,
      "volume": 4633190.0
    },
    {
      "time": "2026-03-25",
      "open": 199.0,
      "high": 210.0,
      "low": 199.0,
      "close": 203.5,
      "volume": 7192240.0
    },
    {
      "time": "2026-03-26",
      "open": 207.5,
      "high": 211.5,
      "low": 198.5,
      "close": 198.5,
      "volume": 9624054.0
    },
    {
      "time": "2026-03-27",
      "open": 195.0,
      "high": 196.0,
      "low": 192.0,
      "close": 195.0,
      "volume": 6164630.0
    },
    {
      "time": "2026-03-30",
      "open": 189.0,
      "high": 198.0,
      "low": 188.0,
      "close": 196.0,
      "volume": 5917957.0
    },
    {
      "time": "2026-03-31",
      "open": 194.0,
      "high": 196.0,
      "low": 185.5,
      "close": 187.0,
      "volume": 7673805.0
    },
    {
      "time": "2026-04-01",
      "open": 195.0,
      "high": 197.5,
      "low": 194.5,
      "close": 195.0,
      "volume": 6679157.0
    },
    {
      "time": "2026-04-02",
      "open": 199.5,
      "high": 209.5,
      "low": 197.5,
      "close": 202.0,
      "volume": 13058004.0
    },
    {
      "time": "2026-04-07",
      "open": 205.5,
      "high": 206.0,
      "low": 191.0,
      "close": 192.0,
      "volume": 13094478.0
    },
    {
      "time": "2026-04-08",
      "open": 200.0,
      "high": 211.0,
      "low": 199.5,
      "close": 211.0,
      "volume": 10585239.0
    },
    {
      "time": "2026-04-09",
      "open": 212.0,
      "high": 219.0,
      "low": 208.5,
      "close": 209.5,
      "volume": 13318808.0
    },
    {
      "time": "2026-04-10",
      "open": 214.0,
      "high": 217.5,
      "low": 212.0,
      "close": 214.5,
      "volume": 10746500.0
    },
    {
      "time": "2026-04-13",
      "open": 219.0,
      "high": 220.5,
      "low": 211.0,
      "close": 218.5,
      "volume": 11007974.0
    },
    {
      "time": "2026-04-14",
      "open": 234.5,
      "high": 237.5,
      "low": 217.0,
      "close": 217.5,
      "volume": 26374023.0
    },
    {
      "time": "2026-04-15",
      "open": 218.5,
      "high": 218.5,
      "low": 207.0,
      "close": 210.0,
      "volume": 15742313.0
    },
    {
      "time": "2026-04-16",
      "open": 210.5,
      "high": 217.0,
      "low": 208.5,
      "close": 212.5,
      "volume": 9445588.0
    },
    {
      "time": "2026-04-17",
      "open": 212.5,
      "high": 212.5,
      "low": 206.0,
      "close": 207.5,
      "volume": 8355427.0
    },
    {
      "time": "2026-04-20",
      "open": 209.0,
      "high": 212.0,
      "low": 206.0,
      "close": 208.0,
      "volume": 9838289.0
    },
    {
      "time": "2026-04-21",
      "open": 211.5,
      "high": 217.5,
      "low": 210.5,
      "close": 213.0,
      "volume": 13028038.0
    },
    {
      "time": "2026-04-22",
      "open": 215.0,
      "high": 224.0,
      "low": 211.5,
      "close": 218.5,
      "volume": 17552910.0
    },
    {
      "time": "2026-04-23",
      "open": 225.0,
      "high": 225.5,
      "low": 203.0,
      "close": 207.0,
      "volume": 21061559.0
    },
    {
      "time": "2026-04-24",
      "open": 209.0,
      "high": 213.0,
      "low": 207.5,
      "close": 210.0,
      "volume": 9866699.0
    },
    {
      "time": "2026-04-27",
      "open": 214.5,
      "high": 224.5,
      "low": 212.0,
      "close": 217.0,
      "volume": 17340715.0
    },
    {
      "time": "2026-04-28",
      "open": 219.5,
      "high": 222.0,
      "low": 213.0,
      "close": 218.5,
      "volume": 11208843.0
    },
    {
      "time": "2026-04-29",
      "open": 219.5,
      "high": 220.0,
      "low": 201.5,
      "close": 204.5,
      "volume": 30442812.0
    },
    {
      "time": "2026-04-30",
      "open": 205.5,
      "high": 210.5,
      "low": 201.0,
      "close": 203.0,
      "volume": 26149433.0
    },
    {
      "time": "2026-05-04",
      "open": 208.0,
      "high": 223.0,
      "low": 208.0,
      "close": 223.0,
      "volume": 27700254.0
    },
    {
      "time": "2026-05-05",
      "open": 224.5,
      "high": 237.0,
      "low": 220.0,
      "close": 227.5,
      "volume": 38739879.0
    },
    {
      "time": "2026-05-06",
      "open": 236.0,
      "high": 250.0,
      "low": 233.5,
      "close": 234.5,
      "volume": 48489760.0
    },
    {
      "time": "2026-05-07",
      "open": 236.0,
      "high": 236.0,
      "low": 226.0,
      "close": 230.5,
      "volume": 22861988.0
    },
    {
      "time": "2026-05-08",
      "open": 227.5,
      "high": 229.5,
      "low": 217.5,
      "close": 222.0,
      "volume": 16620076.0
    },
    {
      "time": "2026-05-11",
      "open": 225.5,
      "high": 231.0,
      "low": 223.0,
      "close": 225.5,
      "volume": 15003946.0
    },
    {
      "time": "2026-05-12",
      "open": 227.5,
      "high": 233.0,
      "low": 219.0,
      "close": 226.5,
      "volume": 18062376.0
    },
    {
      "time": "2026-05-13",
      "open": 224.0,
      "high": 232.0,
      "low": 220.0,
      "close": 232.0,
      "volume": 12744024.0
    },
    {
      "time": "2026-05-14",
      "open": 233.0,
      "high": 236.5,
      "low": 226.5,
      "close": 229.0,
      "volume": 20525774.0
    },
    {
      "time": "2026-05-15",
      "open": 232.5,
      "high": 251.5,
      "low": 231.5,
      "close": 248.0,
      "volume": 56525778.0
    },
    {
      "time": "2026-05-18",
      "open": 245.5,
      "high": 253.5,
      "low": 240.0,
      "close": 250.0,
      "volume": 44344455.0
    },
    {
      "time": "2026-05-19",
      "open": 246.5,
      "high": 246.5,
      "low": 225.5,
      "close": 227.0,
      "volume": 34157853.0
    },
    {
      "time": "2026-05-20",
      "open": 225.0,
      "high": 240.5,
      "low": 224.5,
      "close": 234.5,
      "volume": 20428858.0
    },
    {
      "time": "2026-05-21",
      "open": 246.5,
      "high": 257.5,
      "low": 246.5,
      "close": 257.5,
      "volume": 25307576.0
    }
  ],
  "ma": {
    "ma_20": [
      null,
      null,
      null,
      null,
      null,
      null,
      null,
      null,
      null,
      null,
      null,
      null,
      null,
      null,
      null,
      null,
      null,
      null,
      null,
      124.8,
      126.225,
      127.725,
      129.4,
      131.025,
      132.625,
      134.2,
      135.8,
      136.85,
      138.2,
      139.575,
      141.15,
      142.75,
      144.625,
      146.2,
      147.85,
      149.175,
      150.075,
      150.475,
      150.725,
      150.975,
      151.525,
      151.65,
      151.7,
      151.65,
      152.15,
      153.425,
      155.0,
      156.85,
      158.2,
      159.5,
      160.65,
      161.675,
      162.275,
      162.875,
      163.525,
      164.325,
      165.35,
      166.35,
      166.575,
      167.125,
      167.35,
      167.45,
      167.8,
      167.85,
      167.4,
      166.175,
      164.8,
      163.725,
      162.925,
      161.95,
      161.025,
      160.325,
      159.625,
      158.975,
      158.375,
      157.925,
      157.475,
      157.075,
      157.15,
      156.875,
      156.625,
      157.025,
      157.175,
      157.575,
      158.6,
      159.2,
      159.7,
      160.675,
      161.65,
      162.725,
      163.6,
      164.85,
      167.125,
      169.475,
      171.75,
      173.875,
      175.925,
      178.825,
      182.825,
      187.45,
      192.55,
      197.6,
      202.65,
      207.275,
      210.65,
      215.325,
      219.425,
      223.55,
      227.9,
      232.225,
      236.35,
      239.875,
      242.025,
      244.675,
      247.025,
      249.075,
      251.05,
      252.2,
      252.1,
      251.675,
      251.25,
      250.975,
      250.75,
      251.075,
      251.75,
      250.425,
      248.95,
      247.3,
      245.375,
      242.425,
      240.375,
      238.45,
      236.45,
      233.65,
      231.225,
      229.15,
      227.725,
      225.85,
      223.925,
      221.375,
      218.525,
      215.825,
      212.85,
      209.7,
      206.85,
      204.65,
      203.55,
      202.425,
      200.775,
      201.2,
      200.95,
      200.9,
      201.6,
      202.425,
      202.725,
      203.225,
      203.05,
      203.175,
      203.75,
      205.075,
      205.825,
      206.15,
      207.075,
      208.25,
      208.675,
      209.475,
      210.875,
      212.15,
      214.275,
      215.25,
      215.875,
      216.425,
      216.825,
      217.55,
      218.5,
      220.275,
      222.4,
      223.35,
      224.425,
      226.375
    ],
    "ma_60": [
      null,
      null,
      null,
      null,
      null,
      null,
      null,
      null,
      null,
      null,
      null,
      null,
      null,
      null,
      null,
      null,
      null,
      null,
      null,
      null,
      null,
      null,
      null,
      null,
      null,
      null,
      null,
      null,
      null,
      null,
      null,
      null,
      null,
      null,
      null,
      null,
      null,
      null,
      null,
      null,
      null,
      null,
      null,
      null,
      null,
      null,
      null,
      null,
      null,
      null,
      null,
      null,
      null,
      null,
      null,
      null,
      null,
      null,
      null,
      147.63333333333333,
      148.36666666666667,
      148.94166666666666,
      149.63333333333333,
      150.175,
      150.725,
      151.26666666666668,
      151.86666666666667,
      152.475,
      153.10833333333332,
      153.675,
      154.275,
      154.91666666666666,
      155.50833333333333,
      156.01666666666668,
      156.58333333333334,
      157.14166666666668,
      157.63333333333333,
      157.96666666666667,
      158.15,
      158.325,
      158.5,
      158.70833333333334,
      158.89166666666668,
      159.025,
      159.38333333333333,
      159.6,
      159.83333333333334,
      160.41666666666666,
      160.925,
      161.39166666666668,
      161.75833333333333,
      162.28333333333333,
      163.00833333333333,
      163.775,
      164.55,
      165.375,
      166.25,
      167.41666666666666,
      168.85,
      170.48333333333332,
      172.175,
      174.025,
      175.875,
      177.56666666666666,
      178.88333333333333,
      180.23333333333332,
      181.30833333333334,
      182.65,
      184.15833333333333,
      185.63333333333333,
      186.99166666666667,
      188.35,
      189.59166666666667,
      191.04166666666666,
      192.38333333333333,
      193.625,
      194.81666666666666,
      196.03333333333333,
      197.35833333333332,
      198.66666666666666,
      200.14166666666668,
      201.86666666666667,
      203.525,
      205.30833333333334,
      207.0,
      208.31666666666666,
      209.35833333333332,
      210.50833333333333,
      211.64166666666668,
      212.45833333333334,
      213.44166666666666,
      214.39166666666668,
      215.2,
      215.93333333333334,
      216.66666666666666,
      217.36666666666667,
      218.23333333333332,
      218.95833333333334,
      219.61666666666667,
      220.16666666666666,
      220.775,
      221.46666666666667,
      222.08333333333334,
      222.68333333333334,
      223.08333333333334,
      223.46666666666667,
      223.975,
      224.425,
      224.68333333333334,
      225.28333333333333,
      225.89166666666668,
      226.40833333333333,
      226.69166666666666,
      226.91666666666666,
      226.99166666666667,
      227.15,
      227.275,
      227.075,
      226.59166666666667,
      226.04166666666666,
      225.2,
      224.31666666666666,
      223.55833333333334,
      223.00833333333333,
      222.425,
      221.51666666666668,
      221.125,
      220.625,
      220.14166666666668,
      219.625,
      219.06666666666666,
      218.59166666666667,
      218.29166666666666,
      217.875,
      217.48333333333332,
      217.55,
      217.725,
      217.45833333333334,
      217.36666666666667,
      217.60833333333332
    ],
    "ma_90": [
      null,
      null,
      null,
      null,
      null,
      null,
      null,
      null,
      null,
      null,
      null,
      null,
      null,
      null,
      null,
      null,
      null,
      null,
      null,
      null,
      null,
      null,
      null,
      null,
      null,
      null,
      null,
      null,
      null,
      null,
      null,
      null,
      null,
      null,
      null,
      null,
      null,
      null,
      null,
      null,
      null,
      null,
      null,
      null,
      null,
      null,
      null,
      null,
      null,
      null,
      null,
      null,
      null,
      null,
      null,
      null,
      null,
      null,
      null,
      null,
      null,
      null,
      null,
      null,
      null,
      null,
      null,
      null,
      null,
      null,
      null,
      null,
      null,
      null,
      null,
      null,
      null,
      null,
      null,
      null,
      null,
      null,
      null,
      null,
      null,
      null,
      null,
      null,
      null,
      151.78333333333333,
      152.4111111111111,
      153.12222222222223,
      154.0611111111111,
      155.01111111111112,
      155.9777777777778,
      156.90555555555557,
      157.8111111111111,
      158.93333333333334,
      160.3,
      161.76666666666668,
      163.3,
      164.88888888888889,
      166.46666666666667,
      167.85555555555555,
      169.11666666666667,
      170.56666666666666,
      171.86666666666667,
      173.15,
      174.4,
      175.65555555555557,
      176.88333333333333,
      178.04444444444445,
      179.0888888888889,
      180.26666666666668,
      181.4,
      182.43333333333334,
      183.42222222222222,
      184.56666666666666,
      185.61111111111111,
      186.67777777777778,
      187.76666666666668,
      188.9388888888889,
      190.05,
      191.1611111111111,
      192.20555555555555,
      193.06666666666666,
      193.8388888888889,
      194.66666666666666,
      195.43333333333334,
      195.9777777777778,
      196.62777777777777,
      197.33333333333334,
      197.92222222222222,
      198.48888888888888,
      198.97222222222223,
      199.26111111111112,
      199.58333333333334,
      199.9,
      200.21666666666667,
      200.42777777777778,
      200.62777777777777,
      200.97222222222223,
      201.2888888888889,
      201.56666666666666,
      201.83333333333334,
      202.02777777777777,
      202.32777777777778,
      202.68333333333334,
      203.03333333333333,
      203.55,
      204.09444444444443,
      204.76666666666668,
      205.43333333333334,
      206.17222222222222,
      206.82222222222222,
      207.49444444444444,
      208.08333333333334,
      208.66666666666666,
      209.2888888888889,
      210.01111111111112,
      210.58333333333334,
      211.15555555555557,
      211.83333333333334,
      212.51666666666668,
      213.01111111111112,
      213.48333333333332,
      214.19444444444446,
      214.92222222222222,
      215.7277777777778,
      216.5222222222222,
      217.26111111111112,
      217.96666666666667,
      218.6888888888889,
      219.5,
      220.13333333333333,
      221.06666666666666,
      222.01666666666668,
      222.59444444444443,
      223.23888888888888,
      224.15555555555557
    ]
  },
  "etf_events": [
    {
      "time": "2026-04-02",
      "etf": "00994A",
      "action": "建倉",
      "shares": 25
    },
    {
      "time": "2026-04-15",
      "etf": "00994A",
      "action": "清倉",
      "shares": 25
    }
  ],
  "key_prices": {
    "lines": [
      {
        "price": "274.5",
        "color": "black",
        "text": null,
        "adjective": null,
        "category": "key_price"
      },
      {
        "price": "261",
        "color": "black",
        "text": null,
        "adjective": null,
        "category": "key_price"
      },
      {
        "price": "253.5",
        "color": "black",
        "text": null,
        "adjective": null,
        "category": "key_price"
      },
      {
        "price": "222",
        "color": "gray",
        "text": "內撐",
        "adjective": "small",
        "category": "inner_support"
      },
      {
        "price": "186",
        "color": "red",
        "text": null,
        "adjective": null,
        "category": "key_price"
      },
      {
        "price": "150",
        "color": "red",
        "text": null,
        "adjective": null,
        "category": "key_price"
      }
    ],
    "areas": [
      {
        "low": "253.5",
        "high": "261",
        "text": "賣盤訂單塊",
        "adjective": null,
        "category": "order_block"
      }
    ]
  },
  "events": [
    {
      "time": "2025-09-17",
      "type": "breakdown",
      "category": "key_price",
      "price": "150"
    },
    {
      "time": "2025-09-18",
      "type": "breakdown",
      "category": "key_price",
      "price": "150"
    },
    {
      "time": "2025-09-22",
      "type": "standing",
      "category": "key_price",
      "price": "150"
    },
    {
      "time": "2025-09-25",
      "type": "standing",
      "category": "key_price",
      "price": "150"
    },
    {
      "time": "2025-10-03",
      "type": "standing",
      "category": "key_price",
      "price": "150"
    },
    {
      "time": "2025-10-16",
      "type": "standing",
      "category": "key_price",
      "price": "150"
    },
    {
      "time": "2025-10-23",
      "type": "standing",
      "category": "key_price",
      "price": "150"
    },
    {
      "time": "2025-11-24",
      "type": "standing",
      "category": "key_price",
      "price": "150"
    },
    {
      "time": "2026-01-06",
      "type": "standing",
      "category": "key_price",
      "price": "186"
    },
    {
      "time": "2026-01-16",
      "type": "standing",
      "category": "key_price",
      "price": "253.5"
    },
    {
      "time": "2026-01-16",
      "type": "standing",
      "category": "order_block",
      "price": "253.5-261"
    },
    {
      "time": "2026-01-19",
      "type": "standing",
      "category": "key_price",
      "price": "261"
    },
    {
      "time": "2026-01-21",
      "type": "breakdown",
      "category": "key_price",
      "price": "253.5"
    },
    {
      "time": "2026-01-21",
      "type": "breakdown",
      "category": "order_block",
      "price": "253.5-261"
    },
    {
      "time": "2026-01-23",
      "type": "breakdown",
      "category": "key_price",
      "price": "261"
    },
    {
      "time": "2026-01-27",
      "type": "standing",
      "category": "key_price",
      "price": "253.5"
    },
    {
      "time": "2026-01-27",
      "type": "standing",
      "category": "order_block",
      "price": "253.5-261"
    },
    {
      "time": "2026-01-28",
      "type": "standing",
      "category": "key_price",
      "price": "261"
    },
    {
      "time": "2026-01-29",
      "type": "breakdown",
      "category": "key_price",
      "price": "274.5"
    },
    {
      "time": "2026-01-30",
      "type": "breakdown",
      "category": "key_price",
      "price": "261"
    },
    {
      "time": "2026-01-30",
      "type": "breakdown",
      "category": "order_block",
      "price": "253.5-261"
    },
    {
      "time": "2026-01-30",
      "type": "standing",
      "category": "key_price",
      "price": "253.5"
    },
    {
      "time": "2026-02-02",
      "type": "breakdown",
      "category": "key_price",
      "price": "261"
    },
    {
      "time": "2026-02-02",
      "type": "breakdown",
      "category": "order_block",
      "price": "253.5-261"
    },
    {
      "time": "2026-02-04",
      "type": "breakdown",
      "category": "key_price",
      "price": "261"
    },
    {
      "time": "2026-02-04",
      "type": "breakdown",
      "category": "order_block",
      "price": "253.5-261"
    },
    {
      "time": "2026-02-05",
      "type": "breakdown",
      "category": "key_price",
      "price": "253.5"
    },
    {
      "time": "2026-02-05",
      "type": "breakdown",
      "category": "order_block",
      "price": "253.5-261"
    },
    {
      "time": "2026-02-10",
      "type": "breakdown",
      "category": "key_price",
      "price": "253.5"
    },
    {
      "time": "2026-02-25",
      "type": "breakdown",
      "category": "key_price",
      "price": "261"
    },
    {
      "time": "2026-02-25",
      "type": "standing",
      "category": "key_price",
      "price": "253.5"
    },
    {
      "time": "2026-02-25",
      "type": "standing",
      "category": "order_block",
      "price": "253.5-261"
    },
    {
      "time": "2026-02-26",
      "type": "breakdown",
      "category": "key_price",
      "price": "261"
    },
    {
      "time": "2026-03-02",
      "type": "breakdown",
      "category": "key_price",
      "price": "261"
    },
    {
      "time": "2026-03-03",
      "type": "breakdown",
      "category": "key_price",
      "price": "253.5"
    },
    {
      "time": "2026-03-04",
      "type": "breakdown",
      "category": "key_price",
      "price": "253.5"
    },
    {
      "time": "2026-03-06",
      "type": "standing",
      "category": "inner_support",
      "price": "222"
    },
    {
      "time": "2026-04-01",
      "type": "standing",
      "category": "key_price",
      "price": "186"
    },
    {
      "time": "2026-04-15",
      "type": "breakdown",
      "category": "inner_support",
      "price": "222"
    },
    {
      "time": "2026-04-24",
      "type": "breakdown",
      "category": "inner_support",
      "price": "222"
    },
    {
      "time": "2026-04-28",
      "type": "breakdown",
      "category": "inner_support",
      "price": "222"
    },
    {
      "time": "2026-04-29",
      "type": "breakdown",
      "category": "inner_support",
      "price": "222"
    },
    {
      "time": "2026-05-05",
      "type": "standing",
      "category": "inner_support",
      "price": "222"
    },
    {
      "time": "2026-05-11",
      "type": "standing",
      "category": "inner_support",
      "price": "222"
    },
    {
      "time": "2026-05-14",
      "type": "standing",
      "category": "inner_support",
      "price": "222"
    },
    {
      "time": "2026-05-19",
      "type": "breakdown",
      "category": "key_price",
      "price": "253.5"
    }
  ]
}