{
  "generated_at": "2026-07-09T08:30:01+08:00",
  "sources_ok": 7,
  "sources_failed": 0,
  "errors": [],
  "data": {
    "taiex": {
      "label": "加權指數",
      "value": 45734.41,
      "source": "TWSE OpenAPI MI_INDEX",
      "change": 255.3,
      "change_pct": 0.56,
      "date": "2026-07-08"
    },
    "sp500": {
      "label": "S&P 500",
      "value": 7482.71,
      "source": "yfinance ^GSPC",
      "change": -21.14,
      "change_pct": -0.28
    },
    "nasdaq": {
      "label": "Nasdaq",
      "value": 25870.65,
      "source": "yfinance ^IXIC",
      "change": 51.96,
      "change_pct": 0.2
    },
    "vix": {
      "label": "VIX 恐慌",
      "value": 16.9,
      "source": "yfinance ^VIX",
      "change": 0.77,
      "change_pct": 4.77
    },
    "nikkei": {
      "label": "日經 225",
      "value": 67996.62,
      "source": "yfinance ^N225",
      "change": -260.34,
      "change_pct": -0.38
    },
    "dxy": {
      "label": "美元指數",
      "value": 100.97,
      "source": "yfinance DX-Y.NYB",
      "change": -0.17,
      "change_pct": -0.16
    },
    "margin": {
      "label": "融資餘額",
      "value": 8253.3,
      "source": "TWSE MI_MARGN(MS)+ TPEx margin/balance(金額彙總)",
      "change": 40.7,
      "change_pct": 0.5,
      "date": "2026-07-08",
      "unit": "億元",
      "streak": 1,
      "percentile": 99,
      "history_days": 252
    }
  }
}