{
  "code": "3017",
  "symbol": "TWSE:3017",
  "name": "奇鋐",
  "sector": "散熱",
  "market": "TW",
  "data_date": "2026-07-06",
  "data_through": "2026-07-06",
  "version": "2.1",
  "ohlcv": [
    {
      "time": "2025-10-03",
      "open": 1115.0,
      "high": 1165.0,
      "low": 1090.0,
      "close": 1165.0,
      "volume": 11934596.0
    },
    {
      "time": "2025-10-07",
      "open": 1195.0,
      "high": 1200.0,
      "low": 1135.0,
      "close": 1150.0,
      "volume": 9519860.0
    },
    {
      "time": "2025-10-08",
      "open": 1150.0,
      "high": 1160.0,
      "low": 1110.0,
      "close": 1145.0,
      "volume": 7252745.0
    },
    {
      "time": "2025-10-09",
      "open": 1165.0,
      "high": 1175.0,
      "low": 1130.0,
      "close": 1170.0,
      "volume": 6332081.0
    },
    {
      "time": "2025-10-13",
      "open": 1085.0,
      "high": 1160.0,
      "low": 1085.0,
      "close": 1160.0,
      "volume": 6936997.0
    },
    {
      "time": "2025-10-14",
      "open": 1180.0,
      "high": 1230.0,
      "low": 1155.0,
      "close": 1155.0,
      "volume": 13218749.0
    },
    {
      "time": "2025-10-15",
      "open": 1180.0,
      "high": 1230.0,
      "low": 1165.0,
      "close": 1220.0,
      "volume": 9881168.0
    },
    {
      "time": "2025-10-16",
      "open": 1230.0,
      "high": 1230.0,
      "low": 1180.0,
      "close": 1195.0,
      "volume": 5608061.0
    },
    {
      "time": "2025-10-17",
      "open": 1190.0,
      "high": 1220.0,
      "low": 1145.0,
      "close": 1150.0,
      "volume": 7185867.0
    },
    {
      "time": "2025-10-20",
      "open": 1170.0,
      "high": 1175.0,
      "low": 1135.0,
      "close": 1140.0,
      "volume": 6220482.0
    },
    {
      "time": "2025-10-21",
      "open": 1150.0,
      "high": 1200.0,
      "low": 1150.0,
      "close": 1155.0,
      "volume": 5845773.0
    },
    {
      "time": "2025-10-22",
      "open": 1130.0,
      "high": 1180.0,
      "low": 1120.0,
      "close": 1175.0,
      "volume": 4495878.0
    },
    {
      "time": "2025-10-23",
      "open": 1160.0,
      "high": 1175.0,
      "low": 1150.0,
      "close": 1170.0,
      "volume": 3790271.0
    },
    {
      "time": "2025-10-27",
      "open": 1205.0,
      "high": 1220.0,
      "low": 1180.0,
      "close": 1190.0,
      "volume": 5879927.0
    },
    {
      "time": "2025-10-28",
      "open": 1245.0,
      "high": 1305.0,
      "low": 1240.0,
      "close": 1300.0,
      "volume": 13557543.0
    },
    {
      "time": "2025-10-29",
      "open": 1320.0,
      "high": 1335.0,
      "low": 1290.0,
      "close": 1330.0,
      "volume": 7916687.0
    },
    {
      "time": "2025-10-30",
      "open": 1370.0,
      "high": 1425.0,
      "low": 1360.0,
      "close": 1410.0,
      "volume": 11618364.0
    },
    {
      "time": "2025-10-31",
      "open": 1440.0,
      "high": 1440.0,
      "low": 1395.0,
      "close": 1425.0,
      "volume": 6889584.0
    },
    {
      "time": "2025-11-03",
      "open": 1450.0,
      "high": 1495.0,
      "low": 1445.0,
      "close": 1495.0,
      "volume": 6609856.0
    },
    {
      "time": "2025-11-04",
      "open": 1510.0,
      "high": 1510.0,
      "low": 1430.0,
      "close": 1435.0,
      "volume": 5815364.0
    },
    {
      "time": "2025-11-05",
      "open": 1395.0,
      "high": 1475.0,
      "low": 1390.0,
      "close": 1445.0,
      "volume": 11014399.0
    },
    {
      "time": "2025-11-06",
      "open": 1485.0,
      "high": 1510.0,
      "low": 1470.0,
      "close": 1495.0,
      "volume": 6544619.0
    },
    {
      "time": "2025-11-07",
      "open": 1480.0,
      "high": 1510.0,
      "low": 1465.0,
      "close": 1465.0,
      "volume": 6163276.0
    },
    {
      "time": "2025-11-10",
      "open": 1505.0,
      "high": 1570.0,
      "low": 1460.0,
      "close": 1550.0,
      "volume": 8217203.0
    },
    {
      "time": "2025-11-11",
      "open": 1560.0,
      "high": 1570.0,
      "low": 1520.0,
      "close": 1540.0,
      "volume": 7518454.0
    },
    {
      "time": "2025-11-12",
      "open": 1555.0,
      "high": 1585.0,
      "low": 1500.0,
      "close": 1505.0,
      "volume": 7956940.0
    },
    {
      "time": "2025-11-13",
      "open": 1505.0,
      "high": 1515.0,
      "low": 1470.0,
      "close": 1495.0,
      "volume": 6776412.0
    },
    {
      "time": "2025-11-14",
      "open": 1435.0,
      "high": 1455.0,
      "low": 1400.0,
      "close": 1420.0,
      "volume": 9599190.0
    },
    {
      "time": "2025-11-17",
      "open": 1435.0,
      "high": 1460.0,
      "low": 1410.0,
      "close": 1420.0,
      "volume": 5109601.0
    },
    {
      "time": "2025-11-18",
      "open": 1400.0,
      "high": 1410.0,
      "low": 1370.0,
      "close": 1370.0,
      "volume": 5798659.0
    },
    {
      "time": "2025-11-19",
      "open": 1355.0,
      "high": 1385.0,
      "low": 1335.0,
      "close": 1340.0,
      "volume": 5470504.0
    },
    {
      "time": "2025-11-20",
      "open": 1420.0,
      "high": 1420.0,
      "low": 1330.0,
      "close": 1335.0,
      "volume": 9005212.0
    },
    {
      "time": "2025-11-21",
      "open": 1250.0,
      "high": 1280.0,
      "low": 1205.0,
      "close": 1240.0,
      "volume": 13052742.0
    },
    {
      "time": "2025-11-24",
      "open": 1260.0,
      "high": 1260.0,
      "low": 1210.0,
      "close": 1245.0,
      "volume": 8137459.0
    },
    {
      "time": "2025-11-25",
      "open": 1300.0,
      "high": 1340.0,
      "low": 1240.0,
      "close": 1315.0,
      "volume": 10653298.0
    },
    {
      "time": "2025-11-26",
      "open": 1350.0,
      "high": 1390.0,
      "low": 1340.0,
      "close": 1385.0,
      "volume": 8361725.0
    },
    {
      "time": "2025-11-27",
      "open": 1400.0,
      "high": 1420.0,
      "low": 1370.0,
      "close": 1395.0,
      "volume": 6696881.0
    },
    {
      "time": "2025-11-28",
      "open": 1405.0,
      "high": 1410.0,
      "low": 1375.0,
      "close": 1375.0,
      "volume": 4674610.0
    },
    {
      "time": "2025-12-01",
      "open": 1380.0,
      "high": 1385.0,
      "low": 1330.0,
      "close": 1340.0,
      "volume": 4953191.0
    },
    {
      "time": "2025-12-02",
      "open": 1360.0,
      "high": 1410.0,
      "low": 1310.0,
      "close": 1315.0,
      "volume": 7665974.0
    },
    {
      "time": "2025-12-03",
      "open": 1340.0,
      "high": 1365.0,
      "low": 1320.0,
      "close": 1355.0,
      "volume": 5764345.0
    },
    {
      "time": "2025-12-04",
      "open": 1370.0,
      "high": 1385.0,
      "low": 1325.0,
      "close": 1325.0,
      "volume": 5497875.0
    },
    {
      "time": "2025-12-05",
      "open": 1345.0,
      "high": 1405.0,
      "low": 1340.0,
      "close": 1385.0,
      "volume": 8314708.0
    },
    {
      "time": "2025-12-08",
      "open": 1400.0,
      "high": 1400.0,
      "low": 1370.0,
      "close": 1385.0,
      "volume": 3874259.0
    },
    {
      "time": "2025-12-09",
      "open": 1400.0,
      "high": 1430.0,
      "low": 1380.0,
      "close": 1410.0,
      "volume": 6722511.0
    },
    {
      "time": "2025-12-10",
      "open": 1415.0,
      "high": 1430.0,
      "low": 1390.0,
      "close": 1425.0,
      "volume": 4737458.0
    },
    {
      "time": "2025-12-11",
      "open": 1445.0,
      "high": 1450.0,
      "low": 1405.0,
      "close": 1430.0,
      "volume": 6854831.0
    },
    {
      "time": "2025-12-12",
      "open": 1460.0,
      "high": 1485.0,
      "low": 1425.0,
      "close": 1425.0,
      "volume": 5865475.0
    },
    {
      "time": "2025-12-15",
      "open": 1375.0,
      "high": 1390.0,
      "low": 1365.0,
      "close": 1380.0,
      "volume": 5675750.0
    },
    {
      "time": "2025-12-16",
      "open": 1365.0,
      "high": 1390.0,
      "low": 1340.0,
      "close": 1345.0,
      "volume": 4565277.0
    },
    {
      "time": "2025-12-17",
      "open": 1350.0,
      "high": 1380.0,
      "low": 1340.0,
      "close": 1340.0,
      "volume": 2963422.0
    },
    {
      "time": "2025-12-18",
      "open": 1330.0,
      "high": 1365.0,
      "low": 1325.0,
      "close": 1360.0,
      "volume": 1937359.0
    },
    {
      "time": "2025-12-19",
      "open": 1385.0,
      "high": 1450.0,
      "low": 1380.0,
      "close": 1450.0,
      "volume": 6294902.0
    },
    {
      "time": "2025-12-22",
      "open": 1495.0,
      "high": 1505.0,
      "low": 1465.0,
      "close": 1475.0,
      "volume": 5388668.0
    },
    {
      "time": "2025-12-23",
      "open": 1485.0,
      "high": 1510.0,
      "low": 1475.0,
      "close": 1510.0,
      "volume": 4083157.0
    },
    {
      "time": "2025-12-24",
      "open": 1520.0,
      "high": 1525.0,
      "low": 1485.0,
      "close": 1500.0,
      "volume": 2659963.0
    },
    {
      "time": "2025-12-26",
      "open": 1505.0,
      "high": 1520.0,
      "low": 1495.0,
      "close": 1520.0,
      "volume": 2493370.0
    },
    {
      "time": "2025-12-29",
      "open": 1520.0,
      "high": 1550.0,
      "low": 1505.0,
      "close": 1545.0,
      "volume": 3494079.0
    },
    {
      "time": "2025-12-30",
      "open": 1530.0,
      "high": 1550.0,
      "low": 1525.0,
      "close": 1530.0,
      "volume": 1928354.0
    },
    {
      "time": "2025-12-31",
      "open": 1530.0,
      "high": 1560.0,
      "low": 1510.0,
      "close": 1510.0,
      "volume": 3301831.0
    },
    {
      "time": "2026-01-02",
      "open": 1535.0,
      "high": 1540.0,
      "low": 1440.0,
      "close": 1455.0,
      "volume": 5780257.0
    },
    {
      "time": "2026-01-05",
      "open": 1450.0,
      "high": 1465.0,
      "low": 1430.0,
      "close": 1450.0,
      "volume": 4412179.0
    },
    {
      "time": "2026-01-06",
      "open": 1480.0,
      "high": 1490.0,
      "low": 1410.0,
      "close": 1425.0,
      "volume": 6634971.0
    },
    {
      "time": "2026-01-07",
      "open": 1440.0,
      "high": 1460.0,
      "low": 1375.0,
      "close": 1375.0,
      "volume": 8557829.0
    },
    {
      "time": "2026-01-08",
      "open": 1350.0,
      "high": 1410.0,
      "low": 1345.0,
      "close": 1355.0,
      "volume": 7760960.0
    },
    {
      "time": "2026-01-09",
      "open": 1370.0,
      "high": 1415.0,
      "low": 1360.0,
      "close": 1375.0,
      "volume": 6867721.0
    },
    {
      "time": "2026-01-12",
      "open": 1395.0,
      "high": 1400.0,
      "low": 1340.0,
      "close": 1355.0,
      "volume": 5695057.0
    },
    {
      "time": "2026-01-13",
      "open": 1375.0,
      "high": 1390.0,
      "low": 1335.0,
      "close": 1345.0,
      "volume": 4631863.0
    },
    {
      "time": "2026-01-14",
      "open": 1365.0,
      "high": 1425.0,
      "low": 1360.0,
      "close": 1420.0,
      "volume": 6315542.0
    },
    {
      "time": "2026-01-15",
      "open": 1420.0,
      "high": 1425.0,
      "low": 1360.0,
      "close": 1380.0,
      "volume": 5269664.0
    },
    {
      "time": "2026-01-16",
      "open": 1395.0,
      "high": 1395.0,
      "low": 1350.0,
      "close": 1360.0,
      "volume": 4857493.0
    },
    {
      "time": "2026-01-19",
      "open": 1355.0,
      "high": 1360.0,
      "low": 1275.0,
      "close": 1280.0,
      "volume": 9552812.0
    },
    {
      "time": "2026-01-20",
      "open": 1275.0,
      "high": 1305.0,
      "low": 1265.0,
      "close": 1295.0,
      "volume": 4832354.0
    },
    {
      "time": "2026-01-21",
      "open": 1285.0,
      "high": 1310.0,
      "low": 1280.0,
      "close": 1280.0,
      "volume": 3603028.0
    },
    {
      "time": "2026-01-22",
      "open": 1320.0,
      "high": 1370.0,
      "low": 1265.0,
      "close": 1355.0,
      "volume": 7874222.0
    },
    {
      "time": "2026-01-23",
      "open": 1385.0,
      "high": 1385.0,
      "low": 1355.0,
      "close": 1375.0,
      "volume": 4212687.0
    },
    {
      "time": "2026-01-26",
      "open": 1390.0,
      "high": 1405.0,
      "low": 1365.0,
      "close": 1370.0,
      "volume": 4113584.0
    },
    {
      "time": "2026-01-27",
      "open": 1380.0,
      "high": 1440.0,
      "low": 1375.0,
      "close": 1420.0,
      "volume": 6586873.0
    },
    {
      "time": "2026-01-28",
      "open": 1445.0,
      "high": 1470.0,
      "low": 1430.0,
      "close": 1465.0,
      "volume": 5811271.0
    },
    {
      "time": "2026-01-29",
      "open": 1480.0,
      "high": 1510.0,
      "low": 1450.0,
      "close": 1495.0,
      "volume": 9227577.0
    },
    {
      "time": "2026-01-30",
      "open": 1490.0,
      "high": 1495.0,
      "low": 1400.0,
      "close": 1460.0,
      "volume": 6877370.0
    },
    {
      "time": "2026-02-02",
      "open": 1440.0,
      "high": 1505.0,
      "low": 1415.0,
      "close": 1490.0,
      "volume": 7046740.0
    },
    {
      "time": "2026-02-03",
      "open": 1550.0,
      "high": 1635.0,
      "low": 1545.0,
      "close": 1635.0,
      "volume": 14939322.0
    },
    {
      "time": "2026-02-04",
      "open": 1645.0,
      "high": 1710.0,
      "low": 1625.0,
      "close": 1675.0,
      "volume": 10084274.0
    },
    {
      "time": "2026-02-05",
      "open": 1665.0,
      "high": 1720.0,
      "low": 1630.0,
      "close": 1630.0,
      "volume": 6504909.0
    },
    {
      "time": "2026-02-06",
      "open": 1605.0,
      "high": 1625.0,
      "low": 1535.0,
      "close": 1595.0,
      "volume": 6364872.0
    },
    {
      "time": "2026-02-09",
      "open": 1680.0,
      "high": 1680.0,
      "low": 1585.0,
      "close": 1600.0,
      "volume": 5663608.0
    },
    {
      "time": "2026-02-10",
      "open": 1625.0,
      "high": 1645.0,
      "low": 1590.0,
      "close": 1620.0,
      "volume": 3737625.0
    },
    {
      "time": "2026-02-11",
      "open": 1610.0,
      "high": 1620.0,
      "low": 1560.0,
      "close": 1605.0,
      "volume": 3278642.0
    },
    {
      "time": "2026-02-23",
      "open": 1650.0,
      "high": 1650.0,
      "low": 1515.0,
      "close": 1520.0,
      "volume": 6255420.0
    },
    {
      "time": "2026-02-24",
      "open": 1535.0,
      "high": 1560.0,
      "low": 1510.0,
      "close": 1550.0,
      "volume": 4176128.0
    },
    {
      "time": "2026-02-25",
      "open": 1565.0,
      "high": 1695.0,
      "low": 1560.0,
      "close": 1675.0,
      "volume": 8980346.0
    },
    {
      "time": "2026-02-26",
      "open": 1680.0,
      "high": 1785.0,
      "low": 1665.0,
      "close": 1765.0,
      "volume": 10530482.0
    },
    {
      "time": "2026-03-02",
      "open": 1720.0,
      "high": 1800.0,
      "low": 1715.0,
      "close": 1765.0,
      "volume": 5301930.0
    },
    {
      "time": "2026-03-03",
      "open": 1830.0,
      "high": 1910.0,
      "low": 1780.0,
      "close": 1795.0,
      "volume": 8804200.0
    },
    {
      "time": "2026-03-04",
      "open": 1775.0,
      "high": 1795.0,
      "low": 1670.0,
      "close": 1750.0,
      "volume": 6886787.0
    },
    {
      "time": "2026-03-05",
      "open": 1860.0,
      "high": 1900.0,
      "low": 1795.0,
      "close": 1820.0,
      "volume": 5484692.0
    },
    {
      "time": "2026-03-06",
      "open": 1810.0,
      "high": 1885.0,
      "low": 1785.0,
      "close": 1845.0,
      "volume": 4244526.0
    },
    {
      "time": "2026-03-09",
      "open": 1665.0,
      "high": 1700.0,
      "low": 1665.0,
      "close": 1665.0,
      "volume": 4090895.0
    },
    {
      "time": "2026-03-10",
      "open": 1735.0,
      "high": 1745.0,
      "low": 1665.0,
      "close": 1695.0,
      "volume": 6504366.0
    },
    {
      "time": "2026-03-11",
      "open": 1740.0,
      "high": 1860.0,
      "low": 1740.0,
      "close": 1860.0,
      "volume": 5418586.0
    },
    {
      "time": "2026-03-12",
      "open": 1900.0,
      "high": 1955.0,
      "low": 1870.0,
      "close": 1875.0,
      "volume": 6700536.0
    },
    {
      "time": "2026-03-13",
      "open": 1855.0,
      "high": 1930.0,
      "low": 1815.0,
      "close": 1865.0,
      "volume": 5993158.0
    },
    {
      "time": "2026-03-16",
      "open": 1890.0,
      "high": 1920.0,
      "low": 1830.0,
      "close": 1830.0,
      "volume": 4291909.0
    },
    {
      "time": "2026-03-17",
      "open": 1870.0,
      "high": 1970.0,
      "low": 1860.0,
      "close": 1905.0,
      "volume": 5454630.0
    },
    {
      "time": "2026-03-18",
      "open": 1935.0,
      "high": 1955.0,
      "low": 1850.0,
      "close": 1850.0,
      "volume": 5471887.0
    },
    {
      "time": "2026-03-19",
      "open": 1835.0,
      "high": 2035.0,
      "low": 1835.0,
      "close": 2015.0,
      "volume": 10237997.0
    },
    {
      "time": "2026-03-20",
      "open": 2010.0,
      "high": 2060.0,
      "low": 1945.0,
      "close": 2050.0,
      "volume": 6982270.0
    },
    {
      "time": "2026-03-23",
      "open": 1985.0,
      "high": 2045.0,
      "low": 1955.0,
      "close": 1995.0,
      "volume": 5032899.0
    },
    {
      "time": "2026-03-24",
      "open": 2020.0,
      "high": 2030.0,
      "low": 1915.0,
      "close": 1945.0,
      "volume": 6706925.0
    },
    {
      "time": "2026-03-25",
      "open": 2020.0,
      "high": 2100.0,
      "low": 2015.0,
      "close": 2100.0,
      "volume": 5596612.0
    },
    {
      "time": "2026-03-26",
      "open": 2200.0,
      "high": 2310.0,
      "low": 2175.0,
      "close": 2275.0,
      "volume": 8504254.0
    },
    {
      "time": "2026-03-27",
      "open": 2200.0,
      "high": 2225.0,
      "low": 2120.0,
      "close": 2195.0,
      "volume": 5491400.0
    },
    {
      "time": "2026-03-30",
      "open": 2115.0,
      "high": 2155.0,
      "low": 2075.0,
      "close": 2135.0,
      "volume": 3278469.0
    },
    {
      "time": "2026-03-31",
      "open": 2100.0,
      "high": 2115.0,
      "low": 1945.0,
      "close": 1990.0,
      "volume": 5532841.0
    },
    {
      "time": "2026-04-01",
      "open": 2120.0,
      "high": 2135.0,
      "low": 2065.0,
      "close": 2110.0,
      "volume": 4034786.0
    },
    {
      "time": "2026-04-02",
      "open": 2140.0,
      "high": 2150.0,
      "low": 2065.0,
      "close": 2070.0,
      "volume": 3100871.0
    },
    {
      "time": "2026-04-07",
      "open": 2150.0,
      "high": 2175.0,
      "low": 2015.0,
      "close": 2030.0,
      "volume": 4473019.0
    },
    {
      "time": "2026-04-08",
      "open": 2200.0,
      "high": 2230.0,
      "low": 2150.0,
      "close": 2230.0,
      "volume": 3868944.0
    },
    {
      "time": "2026-04-09",
      "open": 2260.0,
      "high": 2290.0,
      "low": 2200.0,
      "close": 2235.0,
      "volume": 4576820.0
    },
    {
      "time": "2026-04-10",
      "open": 2305.0,
      "high": 2320.0,
      "low": 2230.0,
      "close": 2265.0,
      "volume": 3201925.0
    },
    {
      "time": "2026-04-13",
      "open": 2280.0,
      "high": 2280.0,
      "low": 2185.0,
      "close": 2200.0,
      "volume": 3120709.0
    },
    {
      "time": "2026-04-14",
      "open": 2260.0,
      "high": 2345.0,
      "low": 2260.0,
      "close": 2310.0,
      "volume": 3772108.0
    },
    {
      "time": "2026-04-15",
      "open": 2375.0,
      "high": 2375.0,
      "low": 2310.0,
      "close": 2325.0,
      "volume": 3225805.0
    },
    {
      "time": "2026-04-16",
      "open": 2380.0,
      "high": 2515.0,
      "low": 2365.0,
      "close": 2440.0,
      "volume": 4588118.0
    },
    {
      "time": "2026-04-17",
      "open": 2435.0,
      "high": 2485.0,
      "low": 2375.0,
      "close": 2400.0,
      "volume": 3893545.0
    },
    {
      "time": "2026-04-20",
      "open": 2410.0,
      "high": 2515.0,
      "low": 2395.0,
      "close": 2490.0,
      "volume": 3547518.0
    },
    {
      "time": "2026-04-21",
      "open": 2560.0,
      "high": 2585.0,
      "low": 2450.0,
      "close": 2565.0,
      "volume": 4104167.0
    },
    {
      "time": "2026-04-22",
      "open": 2585.0,
      "high": 2800.0,
      "low": 2580.0,
      "close": 2695.0,
      "volume": 5129543.0
    },
    {
      "time": "2026-04-23",
      "open": 2770.0,
      "high": 2875.0,
      "low": 2585.0,
      "close": 2680.0,
      "volume": 6812966.0
    },
    {
      "time": "2026-04-24",
      "open": 2770.0,
      "high": 2945.0,
      "low": 2760.0,
      "close": 2945.0,
      "volume": 5243084.0
    },
    {
      "time": "2026-04-27",
      "open": 2990.0,
      "high": 3010.0,
      "low": 2820.0,
      "close": 2835.0,
      "volume": 6583986.0
    },
    {
      "time": "2026-04-28",
      "open": 2885.0,
      "high": 2990.0,
      "low": 2755.0,
      "close": 2780.0,
      "volume": 5933190.0
    },
    {
      "time": "2026-04-29",
      "open": 2735.0,
      "high": 2895.0,
      "low": 2735.0,
      "close": 2835.0,
      "volume": 4122743.0
    },
    {
      "time": "2026-04-30",
      "open": 2840.0,
      "high": 2870.0,
      "low": 2805.0,
      "close": 2835.0,
      "volume": 3347271.0
    },
    {
      "time": "2026-05-04",
      "open": 2920.0,
      "high": 2975.0,
      "low": 2815.0,
      "close": 2885.0,
      "volume": 3728835.0
    },
    {
      "time": "2026-05-05",
      "open": 2815.0,
      "high": 2845.0,
      "low": 2655.0,
      "close": 2705.0,
      "volume": 8357094.0
    },
    {
      "time": "2026-05-06",
      "open": 2680.0,
      "high": 2685.0,
      "low": 2435.0,
      "close": 2435.0,
      "volume": 11438234.0
    },
    {
      "time": "2026-05-07",
      "open": 2445.0,
      "high": 2500.0,
      "low": 2380.0,
      "close": 2415.0,
      "volume": 11110013.0
    },
    {
      "time": "2026-05-08",
      "open": 2405.0,
      "high": 2500.0,
      "low": 2350.0,
      "close": 2445.0,
      "volume": 5929295.0
    },
    {
      "time": "2026-05-11",
      "open": 2485.0,
      "high": 2590.0,
      "low": 2455.0,
      "close": 2555.0,
      "volume": 6204661.0
    },
    {
      "time": "2026-05-12",
      "open": 2625.0,
      "high": 2625.0,
      "low": 2520.0,
      "close": 2520.0,
      "volume": 5010847.0
    },
    {
      "time": "2026-05-13",
      "open": 2545.0,
      "high": 2625.0,
      "low": 2500.0,
      "close": 2585.0,
      "volume": 6259261.0
    },
    {
      "time": "2026-05-14",
      "open": 2700.0,
      "high": 2775.0,
      "low": 2555.0,
      "close": 2555.0,
      "volume": 7161071.0
    },
    {
      "time": "2026-05-15",
      "open": 2690.0,
      "high": 2735.0,
      "low": 2445.0,
      "close": 2455.0,
      "volume": 6639560.0
    },
    {
      "time": "2026-05-18",
      "open": 2350.0,
      "high": 2435.0,
      "low": 2300.0,
      "close": 2410.0,
      "volume": 4751185.0
    },
    {
      "time": "2026-05-19",
      "open": 2455.0,
      "high": 2470.0,
      "low": 2370.0,
      "close": 2390.0,
      "volume": 3542685.0
    },
    {
      "time": "2026-05-20",
      "open": 2425.0,
      "high": 2435.0,
      "low": 2325.0,
      "close": 2340.0,
      "volume": 3495975.0
    },
    {
      "time": "2026-05-21",
      "open": 2445.0,
      "high": 2515.0,
      "low": 2415.0,
      "close": 2495.0,
      "volume": 3762794.0
    },
    {
      "time": "2026-05-22",
      "open": 2550.0,
      "high": 2610.0,
      "low": 2470.0,
      "close": 2545.0,
      "volume": 5501063.0
    },
    {
      "time": "2026-05-25",
      "open": 2625.0,
      "high": 2640.0,
      "low": 2545.0,
      "close": 2575.0,
      "volume": 5688149.0
    },
    {
      "time": "2026-05-26",
      "open": 2590.0,
      "high": 2750.0,
      "low": 2570.0,
      "close": 2725.0,
      "volume": 6224924.0
    },
    {
      "time": "2026-05-27",
      "open": 2800.0,
      "high": 2835.0,
      "low": 2695.0,
      "close": 2700.0,
      "volume": 4369212.0
    },
    {
      "time": "2026-05-28",
      "open": 2740.0,
      "high": 2795.0,
      "low": 2540.0,
      "close": 2580.0,
      "volume": 5073423.0
    },
    {
      "time": "2026-05-29",
      "open": 2680.0,
      "high": 2730.0,
      "low": 2615.0,
      "close": 2665.0,
      "volume": 9249169.0
    },
    {
      "time": "2026-06-01",
      "open": 2705.0,
      "high": 2835.0,
      "low": 2705.0,
      "close": 2785.0,
      "volume": 4948139.0
    },
    {
      "time": "2026-06-02",
      "open": 2800.0,
      "high": 2835.0,
      "low": 2650.0,
      "close": 2700.0,
      "volume": 4220815.0
    },
    {
      "time": "2026-06-03",
      "open": 2750.0,
      "high": 2965.0,
      "low": 2700.0,
      "close": 2855.0,
      "volume": 6908395.0
    },
    {
      "time": "2026-06-04",
      "open": 2805.0,
      "high": 2820.0,
      "low": 2675.0,
      "close": 2710.0,
      "volume": 4434507.0
    },
    {
      "time": "2026-06-05",
      "open": 2680.0,
      "high": 2680.0,
      "low": 2505.0,
      "close": 2600.0,
      "volume": 4900550.0
    },
    {
      "time": "2026-06-08",
      "open": 2340.0,
      "high": 2570.0,
      "low": 2340.0,
      "close": 2570.0,
      "volume": 4356915.0
    },
    {
      "time": "2026-06-09",
      "open": 2575.0,
      "high": 2575.0,
      "low": 2440.0,
      "close": 2545.0,
      "volume": 6361937.0
    },
    {
      "time": "2026-06-10",
      "open": 2490.0,
      "high": 2505.0,
      "low": 2350.0,
      "close": 2360.0,
      "volume": 5878553.0
    },
    {
      "time": "2026-06-11",
      "open": 2340.0,
      "high": 2445.0,
      "low": 2260.0,
      "close": 2335.0,
      "volume": 4521372.0
    },
    {
      "time": "2026-06-12",
      "open": 2465.0,
      "high": 2480.0,
      "low": 2380.0,
      "close": 2405.0,
      "volume": 2490291.0
    },
    {
      "time": "2026-06-15",
      "open": 2475.0,
      "high": 2475.0,
      "low": 2410.0,
      "close": 2410.0,
      "volume": 2008865.0
    },
    {
      "time": "2026-06-16",
      "open": 2455.0,
      "high": 2470.0,
      "low": 2370.0,
      "close": 2370.0,
      "volume": 3025487.0
    },
    {
      "time": "2026-06-17",
      "open": 2365.0,
      "high": 2440.0,
      "low": 2330.0,
      "close": 2365.0,
      "volume": 3829529.0
    },
    {
      "time": "2026-06-18",
      "open": 2400.0,
      "high": 2425.0,
      "low": 2365.0,
      "close": 2400.0,
      "volume": 3314114.0
    },
    {
      "time": "2026-06-22",
      "open": 2465.0,
      "high": 2490.0,
      "low": 2380.0,
      "close": 2420.0,
      "volume": 3254412.0
    },
    {
      "time": "2026-06-23",
      "open": 2455.0,
      "high": 2475.0,
      "low": 2400.0,
      "close": 2425.0,
      "volume": 2961821.0
    },
    {
      "time": "2026-06-24",
      "open": 2355.0,
      "high": 2590.0,
      "low": 2335.0,
      "close": 2530.0,
      "volume": 6449281.0
    },
    {
      "time": "2026-06-25",
      "open": 2595.0,
      "high": 2635.0,
      "low": 2485.0,
      "close": 2505.0,
      "volume": 3833150.0
    },
    {
      "time": "2026-06-26",
      "open": 2475.0,
      "high": 2475.0,
      "low": 2255.0,
      "close": 2255.0,
      "volume": 6567236.0
    },
    {
      "time": "2026-06-29",
      "open": 2220.0,
      "high": 2315.0,
      "low": 2220.0,
      "close": 2300.0,
      "volume": 3021205.0
    },
    {
      "time": "2026-06-30",
      "open": 2380.0,
      "high": 2530.0,
      "low": 2370.0,
      "close": 2525.0,
      "volume": 4827330.0
    },
    {
      "time": "2026-07-01",
      "open": 2615.0,
      "high": 2665.0,
      "low": 2500.0,
      "close": 2620.0,
      "volume": 5567033.0
    },
    {
      "time": "2026-07-02",
      "open": 2565.0,
      "high": 2745.0,
      "low": 2525.0,
      "close": 2740.0,
      "volume": 5061323.0
    },
    {
      "time": "2026-07-03",
      "open": 2690.0,
      "high": 2780.0,
      "low": 2665.0,
      "close": 2760.0,
      "volume": 4659120.0
    },
    {
      "time": "2026-07-06",
      "open": 2790.0,
      "high": 2790.0,
      "low": 2615.0,
      "close": 2670.0,
      "volume": 3733969.0
    }
  ],
  "ma": {
    "ma_20": [
      null,
      null,
      null,
      null,
      null,
      null,
      null,
      null,
      null,
      null,
      null,
      null,
      null,
      null,
      null,
      null,
      null,
      null,
      null,
      1236.75,
      1250.75,
      1268.0,
      1284.0,
      1303.0,
      1322.0,
      1339.5,
      1353.25,
      1364.5,
      1378.0,
      1389.5,
      1398.75,
      1406.75,
      1410.25,
      1413.0,
      1413.75,
      1416.5,
      1415.75,
      1413.25,
      1405.5,
      1399.5,
      1395.0,
      1386.5,
      1382.5,
      1374.25,
      1367.75,
      1363.75,
      1360.5,
      1360.75,
      1358.75,
      1357.5,
      1357.5,
      1358.75,
      1369.25,
      1380.75,
      1390.5,
      1396.25,
      1402.5,
      1411.0,
      1420.5,
      1430.25,
      1435.25,
      1441.5,
      1443.5,
      1443.0,
      1440.25,
      1437.75,
      1434.0,
      1430.0,
      1432.0,
      1433.75,
      1434.75,
      1430.75,
      1423.0,
      1413.25,
      1405.5,
      1399.25,
      1391.75,
      1385.5,
      1382.25,
      1381.5,
      1381.75,
      1383.75,
      1394.25,
      1409.25,
      1423.0,
      1434.0,
      1446.25,
      1460.0,
      1469.25,
      1476.25,
      1485.75,
      1505.5,
      1529.0,
      1553.25,
      1575.25,
      1594.0,
      1616.5,
      1637.75,
      1647.75,
      1657.75,
      1677.75,
      1697.0,
      1708.5,
      1716.25,
      1730.0,
      1742.75,
      1763.5,
      1785.0,
      1804.5,
      1825.75,
      1853.25,
      1883.25,
      1904.75,
      1923.25,
      1933.0,
      1951.0,
      1963.5,
      1972.75,
      2001.0,
      2028.0,
      2048.25,
      2064.5,
      2086.75,
      2111.5,
      2138.25,
      2165.75,
      2189.5,
      2215.25,
      2250.25,
      2287.0,
      2329.25,
      2357.25,
      2386.5,
      2421.5,
      2463.75,
      2502.5,
      2534.25,
      2554.5,
      2563.75,
      2574.25,
      2588.75,
      2604.75,
      2618.5,
      2630.0,
      2630.75,
      2631.25,
      2626.25,
      2615.0,
      2605.0,
      2598.25,
      2579.75,
      2574.25,
      2570.25,
      2557.5,
      2549.0,
      2544.0,
      2543.75,
      2564.75,
      2579.5,
      2587.25,
      2588.0,
      2589.25,
      2578.0,
      2567.0,
      2564.5,
      2564.5,
      2563.5,
      2564.75,
      2560.0,
      2553.75,
      2546.25,
      2536.5,
      2526.75,
      2510.5,
      2492.25,
      2479.25,
      2475.25,
      2469.5,
      2472.0,
      2475.5
    ],
    "ma_60": [
      null,
      null,
      null,
      null,
      null,
      null,
      null,
      null,
      null,
      null,
      null,
      null,
      null,
      null,
      null,
      null,
      null,
      null,
      null,
      null,
      null,
      null,
      null,
      null,
      null,
      null,
      null,
      null,
      null,
      null,
      null,
      null,
      null,
      null,
      null,
      null,
      null,
      null,
      null,
      null,
      null,
      null,
      null,
      null,
      null,
      null,
      null,
      null,
      null,
      null,
      null,
      null,
      null,
      null,
      null,
      null,
      null,
      null,
      null,
      1355.5,
      1360.3333333333333,
      1365.3333333333333,
      1370.0,
      1373.4166666666667,
      1376.6666666666667,
      1380.3333333333333,
      1382.5833333333333,
      1385.0833333333333,
      1389.5833333333333,
      1393.5833333333333,
      1397.0,
      1398.75,
      1400.8333333333333,
      1402.3333333333333,
      1403.25,
      1404.0,
      1403.3333333333333,
      1403.25,
      1402.75,
      1403.75,
      1404.0,
      1403.9166666666667,
      1406.75,
      1408.8333333333333,
      1410.3333333333333,
      1411.8333333333333,
      1413.5833333333333,
      1416.9166666666667,
      1420.0,
      1422.5,
      1426.0,
      1431.6666666666667,
      1440.4166666666667,
      1449.0833333333333,
      1457.0833333333333,
      1463.1666666666667,
      1470.25,
      1478.0833333333333,
      1483.5,
      1489.8333333333333,
      1498.25,
      1507.4166666666667,
      1515.4166666666667,
      1522.8333333333333,
      1531.0833333333333,
      1538.1666666666667,
      1547.9166666666667,
      1558.3333333333333,
      1568.5833333333333,
      1578.5833333333333,
      1591.25,
      1606.5,
      1618.9166666666667,
      1629.9166666666667,
      1637.9166666666667,
      1648.0833333333333,
      1657.25,
      1665.3333333333333,
      1677.0,
      1689.0833333333333,
      1702.5833333333333,
      1715.0833333333333,
      1729.8333333333333,
      1745.6666666666667,
      1763.75,
      1780.8333333333333,
      1799.75,
      1820.0833333333333,
      1841.3333333333333,
      1863.0,
      1889.4166666666667,
      1915.3333333333333,
      1940.0833333333333,
      1966.0,
      1990.6666666666667,
      2015.8333333333333,
      2038.0833333333333,
      2055.0,
      2070.8333333333335,
      2086.6666666666665,
      2104.9166666666665,
      2122.0833333333335,
      2137.9166666666665,
      2152.5833333333335,
      2166.3333333333335,
      2179.9166666666665,
      2193.0833333333335,
      2205.0833333333335,
      2219.9166666666665,
      2237.0,
      2254.0833333333335,
      2271.5833333333335,
      2287.1666666666665,
      2300.75,
      2315.25,
      2332.5,
      2347.1666666666665,
      2364.0,
      2381.4166666666665,
      2396.5,
      2408.3333333333335,
      2419.5,
      2427.75,
      2436.1666666666665,
      2444.5,
      2453.8333333333335,
      2459.75,
      2465.0,
      2471.75,
      2479.6666666666665,
      2485.0833333333335,
      2489.3333333333335,
      2494.5,
      2496.5,
      2501.6666666666665,
      2508.5833333333335,
      2517.75,
      2529.5833333333335,
      2538.4166666666665,
      2545.6666666666665
    ],
    "ma_90": [
      null,
      null,
      null,
      null,
      null,
      null,
      null,
      null,
      null,
      null,
      null,
      null,
      null,
      null,
      null,
      null,
      null,
      null,
      null,
      null,
      null,
      null,
      null,
      null,
      null,
      null,
      null,
      null,
      null,
      null,
      null,
      null,
      null,
      null,
      null,
      null,
      null,
      null,
      null,
      null,
      null,
      null,
      null,
      null,
      null,
      null,
      null,
      null,
      null,
      null,
      null,
      null,
      null,
      null,
      null,
      null,
      null,
      null,
      null,
      null,
      null,
      null,
      null,
      null,
      null,
      null,
      null,
      null,
      null,
      null,
      null,
      null,
      null,
      null,
      null,
      null,
      null,
      null,
      null,
      null,
      null,
      null,
      null,
      null,
      null,
      null,
      null,
      null,
      null,
      1386.5555555555557,
      1390.8333333333333,
      1396.6666666666667,
      1403.5555555555557,
      1410.1666666666667,
      1417.2222222222222,
      1423.8333333333333,
      1430.5,
      1437.7222222222222,
      1443.4444444444443,
      1449.611111111111,
      1457.4444444444443,
      1465.2222222222222,
      1472.9444444444443,
      1480.0555555555557,
      1486.7777777777778,
      1492.5555555555557,
      1499.2777777777778,
      1506.2222222222222,
      1511.7777777777778,
      1517.4444444444443,
      1524.7222222222222,
      1533.388888888889,
      1541.5,
      1548.0,
      1553.0,
      1559.7222222222222,
      1566.111111111111,
      1572.888888888889,
      1581.888888888889,
      1591.5,
      1601.7777777777778,
      1611.388888888889,
      1623.2777777777778,
      1635.2777777777778,
      1647.7777777777778,
      1659.0555555555557,
      1671.2222222222222,
      1684.4444444444443,
      1699.5,
      1714.6666666666667,
      1732.3333333333333,
      1749.111111111111,
      1764.611111111111,
      1780.7222222222222,
      1796.5555555555557,
      1812.7777777777778,
      1826.9444444444443,
      1838.1666666666667,
      1849.6666666666667,
      1861.888888888889,
      1875.388888888889,
      1888.2777777777778,
      1900.888888888889,
      1912.888888888889,
      1923.388888888889,
      1933.5,
      1943.1666666666667,
      1952.0,
      1962.7222222222222,
      1974.2222222222222,
      1986.6666666666667,
      2000.8333333333333,
      2015.0,
      2028.388888888889,
      2042.9444444444443,
      2058.6111111111113,
      2073.5555555555557,
      2090.3333333333335,
      2104.6666666666665,
      2118.222222222222,
      2131.6666666666665,
      2145.722222222222,
      2157.5555555555557,
      2169.277777777778,
      2180.9444444444443,
      2192.4444444444443,
      2203.5555555555557,
      2214.0555555555557,
      2224.4444444444443,
      2234.722222222222,
      2245.4444444444443,
      2257.0,
      2266.6666666666665,
      2273.1111111111113,
      2280.5555555555557,
      2290.8888888888887,
      2302.222222222222,
      2314.6666666666665,
      2327.5,
      2340.277777777778
    ]
  },
  "etf_events": [
    {
      "time": "2025-10-15",
      "etf": "00981A",
      "action": "加碼",
      "shares": 70
    },
    {
      "time": "2025-10-31",
      "etf": "00981A",
      "action": "加碼",
      "shares": 40
    },
    {
      "time": "2025-11-05",
      "etf": "00981A",
      "action": "加碼",
      "shares": 50
    },
    {
      "time": "2025-11-21",
      "etf": "00981A",
      "action": "加碼",
      "shares": 82
    },
    {
      "time": "2025-11-24",
      "etf": "00981A",
      "action": "加碼",
      "shares": 93
    },
    {
      "time": "2025-11-25",
      "etf": "00981A",
      "action": "加碼",
      "shares": 109
    },
    {
      "time": "2025-12-01",
      "etf": "00981A",
      "action": "加碼",
      "shares": 100
    },
    {
      "time": "2025-12-18",
      "etf": "00981A",
      "action": "加碼",
      "shares": 96
    },
    {
      "time": "2025-12-19",
      "etf": "00981A",
      "action": "加碼",
      "shares": 108
    },
    {
      "time": "2025-12-24",
      "etf": "00987A",
      "action": "建倉",
      "shares": 5
    },
    {
      "time": "2025-12-26",
      "etf": "00987A",
      "action": "加碼",
      "shares": 5
    },
    {
      "time": "2025-12-29",
      "etf": "00992A",
      "action": "建倉",
      "shares": 328
    },
    {
      "time": "2025-12-29",
      "etf": "00987A",
      "action": "加碼",
      "shares": 32
    },
    {
      "time": "2025-12-30",
      "etf": "00992A",
      "action": "加碼",
      "shares": 37
    },
    {
      "time": "2025-12-31",
      "etf": "00987A",
      "action": "加碼",
      "shares": 27
    },
    {
      "time": "2026-01-06",
      "etf": "00994A",
      "action": "建倉",
      "shares": 14
    },
    {
      "time": "2026-01-09",
      "etf": "00994A",
      "action": "加碼",
      "shares": 4
    },
    {
      "time": "2026-01-14",
      "etf": "00994A",
      "action": "加碼",
      "shares": 4
    },
    {
      "time": "2026-01-16",
      "etf": "00992A",
      "action": "減碼",
      "shares": 25
    },
    {
      "time": "2026-01-19",
      "etf": "00992A",
      "action": "減碼",
      "shares": 14
    },
    {
      "time": "2026-01-19",
      "etf": "00994A",
      "action": "減碼",
      "shares": 5
    },
    {
      "time": "2026-01-20",
      "etf": "00994A",
      "action": "減碼",
      "shares": 5
    },
    {
      "time": "2026-01-21",
      "etf": "00995A",
      "action": "建倉",
      "shares": 74
    },
    {
      "time": "2026-01-23",
      "etf": "00995A",
      "action": "加碼",
      "shares": 13
    },
    {
      "time": "2026-01-26",
      "etf": "00995A",
      "action": "加碼",
      "shares": 6
    },
    {
      "time": "2026-01-27",
      "etf": "00992A",
      "action": "加碼",
      "shares": 10
    },
    {
      "time": "2026-01-27",
      "etf": "00995A",
      "action": "加碼",
      "shares": 6
    },
    {
      "time": "2026-01-28",
      "etf": "00995A",
      "action": "加碼",
      "shares": 11
    },
    {
      "time": "2026-02-03",
      "etf": "00994A",
      "action": "加碼",
      "shares": 5
    },
    {
      "time": "2026-02-04",
      "etf": "00994A",
      "action": "加碼",
      "shares": 4
    },
    {
      "time": "2026-02-06",
      "etf": "00987A",
      "action": "減碼",
      "shares": 14
    },
    {
      "time": "2026-02-09",
      "etf": "00987A",
      "action": "減碼",
      "shares": 2
    },
    {
      "time": "2026-02-11",
      "etf": "00994A",
      "action": "減碼",
      "shares": 2
    },
    {
      "time": "2026-02-24",
      "etf": "00995A",
      "action": "減碼",
      "shares": 10
    },
    {
      "time": "2026-02-25",
      "etf": "00994A",
      "action": "加碼",
      "shares": 8
    },
    {
      "time": "2026-02-25",
      "etf": "00995A",
      "action": "減碼",
      "shares": 8
    },
    {
      "time": "2026-03-03",
      "etf": "00994A",
      "action": "加碼",
      "shares": 2
    },
    {
      "time": "2026-03-04",
      "etf": "00981A",
      "action": "加碼",
      "shares": 100
    },
    {
      "time": "2026-03-04",
      "etf": "00995A",
      "action": "減碼",
      "shares": 6
    },
    {
      "time": "2026-03-05",
      "etf": "00995A",
      "action": "減碼",
      "shares": 7
    },
    {
      "time": "2026-03-06",
      "etf": "00995A",
      "action": "減碼",
      "shares": 3
    },
    {
      "time": "2026-03-12",
      "etf": "00994A",
      "action": "加碼",
      "shares": 1
    },
    {
      "time": "2026-03-16",
      "etf": "00995A",
      "action": "減碼",
      "shares": 5
    },
    {
      "time": "2026-03-19",
      "etf": "00992A",
      "action": "加碼",
      "shares": 12
    },
    {
      "time": "2026-03-20",
      "etf": "00981A",
      "action": "加碼",
      "shares": 304
    },
    {
      "time": "2026-03-20",
      "etf": "00992A",
      "action": "加碼",
      "shares": 15
    },
    {
      "time": "2026-03-20",
      "etf": "00994A",
      "action": "加碼",
      "shares": 12
    },
    {
      "time": "2026-03-23",
      "etf": "00981A",
      "action": "加碼",
      "shares": 100
    },
    {
      "time": "2026-03-23",
      "etf": "00995A",
      "action": "加碼",
      "shares": 5
    },
    {
      "time": "2026-04-17",
      "etf": "00981A",
      "action": "加碼",
      "shares": 133
    },
    {
      "time": "2026-04-17",
      "etf": "00992A",
      "action": "加碼",
      "shares": 15
    },
    {
      "time": "2026-04-20",
      "etf": "00981A",
      "action": "加碼",
      "shares": 142
    },
    {
      "time": "2026-04-20",
      "etf": "00992A",
      "action": "加碼",
      "shares": 26
    },
    {
      "time": "2026-04-20",
      "etf": "00994A",
      "action": "加碼",
      "shares": 10
    },
    {
      "time": "2026-04-21",
      "etf": "00981A",
      "action": "加碼",
      "shares": 120
    },
    {
      "time": "2026-04-21",
      "etf": "00992A",
      "action": "加碼",
      "shares": 70
    },
    {
      "time": "2026-04-22",
      "etf": "00994A",
      "action": "加碼",
      "shares": 14
    },
    {
      "time": "2026-04-23",
      "etf": "00981A",
      "action": "加碼",
      "shares": 118
    },
    {
      "time": "2026-04-23",
      "etf": "00992A",
      "action": "加碼",
      "shares": 100
    },
    {
      "time": "2026-04-23",
      "etf": "00987A",
      "action": "加碼",
      "shares": 12
    },
    {
      "time": "2026-04-24",
      "etf": "00994A",
      "action": "加碼",
      "shares": 8
    },
    {
      "time": "2026-04-27",
      "etf": "00995A",
      "action": "加碼",
      "shares": 7
    },
    {
      "time": "2026-05-05",
      "etf": "00994A",
      "action": "減碼",
      "shares": 8
    },
    {
      "time": "2026-05-06",
      "etf": "00981A",
      "action": "加碼",
      "shares": 180
    },
    {
      "time": "2026-05-06",
      "etf": "00994A",
      "action": "減碼",
      "shares": 8
    },
    {
      "time": "2026-05-07",
      "etf": "00992A",
      "action": "減碼",
      "shares": 100
    },
    {
      "time": "2026-05-07",
      "etf": "00987A",
      "action": "加碼",
      "shares": 21
    },
    {
      "time": "2026-05-11",
      "etf": "00981A",
      "action": "加碼",
      "shares": 149
    },
    {
      "time": "2026-05-11",
      "etf": "00403A",
      "action": "建倉",
      "shares": 1300
    },
    {
      "time": "2026-05-12",
      "etf": "00403A",
      "action": "加碼",
      "shares": 571
    },
    {
      "time": "2026-05-13",
      "etf": "00981A",
      "action": "加碼",
      "shares": 345
    },
    {
      "time": "2026-05-13",
      "etf": "00994A",
      "action": "加碼",
      "shares": 6
    },
    {
      "time": "2026-05-13",
      "etf": "00403A",
      "action": "加碼",
      "shares": 789
    },
    {
      "time": "2026-05-14",
      "etf": "00987A",
      "action": "清倉",
      "shares": 86
    },
    {
      "time": "2026-05-14",
      "etf": "00994A",
      "action": "加碼",
      "shares": 14
    },
    {
      "time": "2026-05-19",
      "etf": "00403A",
      "action": "加碼",
      "shares": 200
    },
    {
      "time": "2026-05-21",
      "etf": "00403A",
      "action": "加碼",
      "shares": 220
    },
    {
      "time": "2026-05-22",
      "etf": "00403A",
      "action": "加碼",
      "shares": 110
    },
    {
      "time": "2026-05-26",
      "etf": "00994A",
      "action": "加碼",
      "shares": 6
    },
    {
      "time": "2026-05-29",
      "etf": "00992A",
      "action": "加碼",
      "shares": 150
    },
    {
      "time": "2026-06-01",
      "etf": "00992A",
      "action": "加碼",
      "shares": 150
    },
    {
      "time": "2026-06-01",
      "etf": "00994A",
      "action": "加碼",
      "shares": 8
    },
    {
      "time": "2026-06-03",
      "etf": "00994A",
      "action": "加碼",
      "shares": 10
    },
    {
      "time": "2026-06-09",
      "etf": "00992A",
      "action": "加碼",
      "shares": 175
    },
    {
      "time": "2026-06-10",
      "etf": "00992A",
      "action": "加碼",
      "shares": 175
    },
    {
      "time": "2026-06-10",
      "etf": "00994A",
      "action": "減碼",
      "shares": 16
    },
    {
      "time": "2026-06-11",
      "etf": "00992A",
      "action": "加碼",
      "shares": 200
    },
    {
      "time": "2026-06-12",
      "etf": "00992A",
      "action": "加碼",
      "shares": 200
    },
    {
      "time": "2026-06-26",
      "etf": "00994A",
      "action": "減碼",
      "shares": 20
    },
    {
      "time": "2026-06-30",
      "etf": "00403A",
      "action": "加碼",
      "shares": 130
    },
    {
      "time": "2026-07-03",
      "etf": "00995A",
      "action": "減碼",
      "shares": 5
    }
  ],
  "key_prices": {
    "lines": [
      {
        "price": "2390",
        "color": "black",
        "text": "小內撐 2390",
        "adjective": "small",
        "category": "inner_support"
      },
      {
        "price": "1545",
        "color": "red",
        "text": null,
        "adjective": null,
        "category": "key_price"
      }
    ],
    "areas": []
  },
  "key_prices_source": "snapshot",
  "events": [
    {
      "time": "2025-11-13",
      "type": "breakdown",
      "category": "key_price",
      "price": "1545"
    },
    {
      "time": "2025-12-30",
      "type": "breakdown",
      "category": "key_price",
      "price": "1545"
    },
    {
      "time": "2025-12-31",
      "type": "breakdown",
      "category": "key_price",
      "price": "1545"
    },
    {
      "time": "2026-01-02",
      "type": "breakdown",
      "category": "key_price",
      "price": "1545"
    },
    {
      "time": "2026-02-04",
      "type": "standing",
      "category": "key_price",
      "price": "1545"
    },
    {
      "time": "2026-02-09",
      "type": "standing",
      "category": "key_price",
      "price": "1545"
    },
    {
      "time": "2026-02-25",
      "type": "standing",
      "category": "key_price",
      "price": "1545"
    },
    {
      "time": "2026-04-17",
      "type": "standing",
      "category": "inner_support",
      "price": "2390"
    },
    {
      "time": "2026-05-08",
      "type": "standing",
      "category": "inner_support",
      "price": "2390"
    },
    {
      "time": "2026-05-19",
      "type": "standing",
      "category": "inner_support",
      "price": "2390"
    },
    {
      "time": "2026-06-09",
      "type": "standing",
      "category": "inner_support",
      "price": "2390"
    },
    {
      "time": "2026-06-11",
      "type": "breakdown",
      "category": "inner_support",
      "price": "2390"
    },
    {
      "time": "2026-06-15",
      "type": "standing",
      "category": "inner_support",
      "price": "2390"
    },
    {
      "time": "2026-06-17",
      "type": "breakdown",
      "category": "inner_support",
      "price": "2390"
    },
    {
      "time": "2026-06-22",
      "type": "standing",
      "category": "inner_support",
      "price": "2390"
    },
    {
      "time": "2026-06-25",
      "type": "standing",
      "category": "inner_support",
      "price": "2390"
    },
    {
      "time": "2026-06-29",
      "type": "breakdown",
      "category": "inner_support",
      "price": "2390"
    },
    {
      "time": "2026-07-01",
      "type": "standing",
      "category": "inner_support",
      "price": "2390"
    }
  ],
  "chips": {
    "unit": "張",
    "dates": [
      "2026-06-05",
      "2026-06-08",
      "2026-06-09",
      "2026-06-10",
      "2026-06-11",
      "2026-06-12",
      "2026-06-15",
      "2026-06-16",
      "2026-06-17",
      "2026-06-18",
      "2026-06-22",
      "2026-06-23",
      "2026-06-24",
      "2026-06-25",
      "2026-06-26",
      "2026-06-29",
      "2026-06-30",
      "2026-07-02",
      "2026-07-03",
      "2026-07-06"
    ],
    "foreign_net": [
      -504,
      360,
      -676,
      -769,
      112,
      -80,
      -2,
      41,
      531,
      268,
      323,
      37,
      862,
      -345,
      -2054,
      312,
      1694,
      115,
      295,
      -351
    ],
    "trust_net": [
      -193,
      -2,
      33,
      -265,
      318,
      -100,
      -148,
      -736,
      -1292,
      -453,
      -283,
      58,
      -105,
      159,
      166,
      214,
      259,
      1232,
      399,
      195
    ],
    "margin": [
      null,
      null,
      null,
      null,
      null,
      null,
      null,
      null,
      null,
      null,
      null,
      null,
      null,
      null,
      null,
      null,
      null,
      null,
      4251,
      4251
    ],
    "trust_markers": [
      {
        "time": "2026-06-09",
        "value": 33
      },
      {
        "time": "2026-06-11",
        "value": 318
      },
      {
        "time": "2026-06-23",
        "value": 58
      },
      {
        "time": "2026-06-25",
        "value": 159
      },
      {
        "time": "2026-06-26",
        "value": 166
      },
      {
        "time": "2026-06-29",
        "value": 214
      },
      {
        "time": "2026-06-30",
        "value": 259
      },
      {
        "time": "2026-07-02",
        "value": 1232
      },
      {
        "time": "2026-07-03",
        "value": 399
      },
      {
        "time": "2026-07-06",
        "value": 195
      }
    ],
    "large_holder": {
      "date": "2026-07-03",
      "ratio": 52.77
    }
  }
}